{
  "version": 4,
  "name": "12ballfar",
  "updatedAt": "2026-04-22T23:24:59.646834Z",
  "fieldSize": 3.66,
  "backgroundImageFilename": "6fb5ea3496da8d70c2dfe3ae7babf07384dd2f611379c1161f142f4677d83275.svg",
  "backgroundSettings": {
    "scale": 1,
    "rotation": 90,
    "opacity": 1,
    "mirrorH": false,
    "mirrorV": false
  },
  "variables": {
    "vars": [],
    "linkedFrom": null
  },
  "robotParams": {
    "mass": 15,
    "inertia": 0.3,
    "wheel_radius": 0.048,
    "lx": 0.148,
    "ly": 0.15,
    "w_max": 40.4711111111,
    "t_max": 1.5,
    "f_traction_max": 10,
    "default_intake_distance": 0.5,
    "default_intake_velocity": 1,
    "linkedFrom": "test12ball.json"
  },
  "fragments": [],
  "groupNames": [],
  "trajectories": [
    {
      "id": "cfd304e0-9977-48fe-8048-0ec292718a97",
      "name": "Trajectory 1",
      "waypoints": [
        {
          "x": 0.315675,
          "y": -1.58295,
          "heading": 0,
          "stop": true,
          "v_max": 3,
          "omega_max": 10,
          "type": "constrained",
          "intake_x": 0.8156749999999999,
          "intake_y": -1.58295,
          "intake_distance": 0.5,
          "intake_velocity_max": 1,
          "intake_velocity_slack": 0.1
        },
        {
          "x": 0.90585,
          "y": -0.928725,
          "heading": 0,
          "stop": false,
          "v_max": 3,
          "omega_max": 10,
          "type": "constrained",
          "intake_x": 1.40585,
          "intake_y": -0.928725,
          "intake_distance": 0.5,
          "intake_velocity_max": 1,
          "intake_velocity_slack": 0.1
        },
        {
          "x": 1.486875,
          "y": -0.92415,
          "heading": 0,
          "stop": false,
          "v_max": 3,
          "omega_max": 10,
          "type": "constrained",
          "intake_x": 1.986875,
          "intake_y": -0.92415,
          "intake_distance": 0.5,
          "intake_velocity_max": 1,
          "intake_velocity_slack": 0.1
        },
        {
          "x": 0.2733704432225537,
          "y": -1.3418309885764041,
          "heading": 0,
          "stop": true,
          "v_max": 3,
          "omega_max": 10,
          "type": "unconstrained",
          "intake_x": 0.7928,
          "intake_y": -1.464,
          "intake_distance": 0.5,
          "intake_velocity_max": 1,
          "intake_velocity_slack": 0.1
        }
      ],
      "constraints": [
        {
          "id": "32505dd0-5c60-4042-96d2-4f43c888ba64",
          "type": "heading-tangent",
          "fromWaypoint": 1,
          "toWaypoint": 2,
          "params": {},
          "enabled": true
        },
        {
          "id": "643a2577-05d5-4793-bc39-925a5a0de139",
          "type": "max-omega",
          "fromWaypoint": 1,
          "toWaypoint": 2,
          "params": {
            "omega_max": 0.1
          },
          "enabled": true
        },
        {
          "id": "0575e897-8748-4a9e-a783-da0e6c472701",
          "type": "max-omega",
          "fromWaypoint": 0,
          "toWaypoint": 3,
          "params": {
            "omega_max": 5
          },
          "enabled": true
        }
      ],
      "eventMarkers": [],
      "solverSettings": {
        "samplesPerMeter": 20,
        "minSamplesPerSegment": 3,
        "controlEffortWeight": 0.03
      },
      "trajectory": {
        "times": [
          0,
          0.0630617886288468,
          0.1261235772576936,
          0.1891853658865404,
          0.2522471545153872,
          0.315308943144234,
          0.37837073177308084,
          0.44143252040192765,
          0.5044943090307744,
          0.5675560976596212,
          0.630617886288468,
          0.6936796749173149,
          0.7567414635461617,
          0.8198032521750085,
          0.8828650408038553,
          0.9459268294327021,
          1.0089886180615488,
          1.0720504066903955,
          1.1351121953192422,
          1.1924773311653223,
          1.2498424670114023,
          1.3072076028574824,
          1.3645727387035624,
          1.4219378745496425,
          1.4793030103957225,
          1.5366681462418026,
          1.5940332820878826,
          1.6513984179339627,
          1.7087635537800427,
          1.7661286896261228,
          1.8234938254722028,
          1.8837663147482462,
          1.9440388040242895,
          2.004311293300333,
          2.0645837825763764,
          2.12485627185242,
          2.1851287611284635,
          2.245401250404507,
          2.3056737396805507,
          2.3659462289565942,
          2.426218718232638,
          2.4864912075086814,
          2.546763696784725,
          2.6070361860607685,
          2.667308675336812,
          2.7275811646128556,
          2.787853653888899,
          2.8481261431649427,
          2.9083986324409863,
          2.96867112171703,
          3.0289436109930734,
          3.089216100269117,
          3.1494885895451605,
          3.209761078821204,
          3.2700335680972477,
          3.330306057373291,
          3.390578546649335
        ],
        "states": [
          [
            0,
            0,
            -2.6297772820237475e-30,
            0.315675,
            -1.58295,
            0
          ],
          [
            2.5787825742935476e-06,
            0.1464428058241774,
            3.1288164880600615e-06,
            0.31567508505510206,
            -1.5781127269727293,
            1.2509957388076994e-07
          ],
          [
            6.541219137423428e-06,
            0.29127542151732727,
            9.394624401983894e-06,
            0.31567537862639095,
            -1.5640936961958132,
            5.729343444602356e-07
          ],
          [
            1.4320655660977997e-05,
            0.4345127432821121,
            2.140185522778472e-05,
            0.3156760485905597,
            -1.5409939570902278,
            1.6454616727579474e-06
          ],
          [
            6.571265967586698e-05,
            0.5761322345608619,
            4.225569928695383e-05,
            0.3156786482679637,
            -1.5089148561685712,
            3.828900884622604e-06
          ],
          [
            0.0276750536115052,
            0.6888031422469826,
            6.7129251849624e-05,
            0.3165929042475579,
            -1.4688612018789877,
            7.4881409411949155e-06
          ],
          [
            0.088117090275415,
            0.7676015715370641,
            8.745238552795856e-05,
            0.32033054542102135,
            -1.4228211897658123,
            1.2534012161866082e-05
          ],
          [
            0.1813103333857319,
            0.81298131432525,
            0.00010191721939867656,
            0.32895937329597885,
            -1.372915890153472,
            1.862726394640037e-05
          ],
          [
            0.3096923831403915,
            0.8228872346303452,
            0.00011182926961518562,
            0.34462508894627236,
            -1.3213206308766334,
            2.5450659926501295e-05
          ],
          [
            0.4570022812336273,
            0.8138720818402475,
            0.00011772434313424408,
            0.3690107391164869,
            -1.2697256869956253,
            3.273851660911318e-05
          ],
          [
            0.6043253256444753,
            0.8049434936531608,
            0.00011742207316367706,
            0.4026864485020424,
            -1.218696397461205,
            4.0150338580724126e-05
          ],
          [
            0.7411850587976403,
            0.7857123358396761,
            3.928042324224281e-05,
            0.44530770063544967,
            -1.1685704721375552,
            4.4430844346190065e-05
          ],
          [
            0.8641091933061303,
            0.7528338620145029,
            -1.5169004439804263e-06,
            0.4961001981853559,
            -1.1201080865205433,
            4.527673734159319e-05
          ],
          [
            0.9763621599556265,
            0.7097077669429381,
            -4.9158274829327664e-05,
            0.5542927474599066,
            -1.0740575687370968,
            4.3276232227238284e-05
          ],
          [
            1.080418840157586,
            0.6589073561528682,
            -0.00010818488261012356,
            0.6192939870985715,
            -1.030980149409469,
            3.781616066626669e-05
          ],
          [
            1.1435314166510604,
            0.5679599503482132,
            -0.0001404343205208491,
            0.6895075560509752,
            -0.9924324170468586,
            2.9704398117684035e-05
          ],
          [
            1.1435469578573672,
            0.415288294371251,
            -0.00015503173378420609,
            0.761621206093225,
            -0.9616588543799295,
            2.026470982196922e-05
          ],
          [
            1.1435519780409924,
            0.2642835573341353,
            -0.00016113490252572587,
            0.8337354914227274,
            -0.9404579767137441,
            1.0244108198292579e-05
          ],
          [
            1.1435541031372136,
            0.11493562607291867,
            -0.00016320210528049747,
            0.90585,
            -0.928725,
            2.2054160192020228e-32
          ],
          [
            1.2635879761138882,
            0.12291530987306783,
            -0.06157507045719595,
            0.9750349203904604,
            -0.9218905897696594,
            -0.0021740722177328647
          ],
          [
            1.3070267314244812,
            0.10771664162104097,
            -0.09985780528960668,
            1.0488179085799443,
            -0.9152866797460752,
            -0.007055764571721985
          ],
          [
            1.248036223336462,
            0.039279993105765534,
            -0.0038961653831763835,
            1.1220347725192144,
            -0.911150153642563,
            -0.009401564421789866
          ],
          [
            1.1618158563963759,
            -0.010016452475746519,
            -0.003812906486340315,
            1.1910534647028301,
            -0.9103717314402967,
            -0.009622133678035268
          ],
          [
            1.052493561185362,
            -0.03537394969283913,
            -0.0037753279020221867,
            1.254436136633612,
            -0.9117049619921818,
            -0.009839536964046661
          ],
          [
            0.9183215357624566,
            -0.035235030056488884,
            -0.0037479923379685103,
            1.3108053366042882,
            -0.9137299876809836,
            -0.01005514560621533
          ],
          [
            0.7827440657272159,
            -0.03362775745755642,
            -0.0037227949689788743,
            1.3594357634283751,
            -0.9157031480728509,
            -0.010269261509392905
          ],
          [
            0.6471603903897837,
            -0.03198553839191775,
            -0.003695761670066398,
            1.4002885844322406,
            -0.9175830994071892,
            -0.01048186724729721
          ],
          [
            0.5115755310813419,
            -0.030312923760098465,
            -0.0036622459519919433,
            1.4333635936114903,
            -0.9193679726447694,
            -0.010692693717226151
          ],
          [
            0.3759917055258513,
            -0.028611045863788608,
            -0.003611417326302172,
            1.4586607892675276,
            -0.9210560573804115,
            -0.010900987289894052
          ],
          [
            0.2404171836900261,
            -0.02688064172512537,
            -0.003464961474868231,
            1.4761804776391854,
            -0.9226456955174971,
            -0.011102994302782217
          ],
          [
            0.13672568941011545,
            -0.0256694532638725,
            0.3171610417960742,
            1.486875,
            -0.92415,
            1.1467519193717912e-31
          ],
          [
            0.01921641406935871,
            -0.026508059533325037,
            0.5539100140492321,
            1.491419926690166,
            -0.9257120100660353,
            0.028021042522861767
          ],
          [
            -0.12215791477229479,
            -0.032584806506725475,
            0.5539417299279975,
            1.4881304324153908,
            -0.9274743871715418,
            0.061407770853025095
          ],
          [
            -0.26321518033561647,
            -0.04398716473292317,
            0.5539550824631956,
            1.4763286167134402,
            -0.9297641139446305,
            0.09479572006855974
          ],
          [
            -0.40376762292045987,
            -0.06074471817742697,
            0.5539629903876908,
            1.4560392387470085,
            -0.9329031634466342,
            0.1281842692837733
          ],
          [
            -0.5436245820351187,
            -0.08287980383036163,
            0.5539681381402782,
            1.4272984661426087,
            -0.9372150734131578,
            0.16157319130955947
          ],
          [
            -0.6825919397817827,
            -0.11040724203484695,
            0.5539712579787538,
            1.390154067778128,
            -0.9430245014538836,
            0.19496234732626386
          ],
          [
            -0.8204722645682095,
            -0.14333407315595567,
            0.5539722907372667,
            1.3446656180971848,
            -0.9506567638855146,
            0.22835161288102024
          ],
          [
            -0.9570649009337768,
            -0.1816593740596623,
            0.5539704543652347,
            1.2909046944584879,
            -0.9604373612047529,
            0.26174083276466553
          ],
          [
            -1.0921653631430328,
            -0.2253743935327821,
            0.5539636068996129,
            1.2289550909403415,
            -0.9726915027471809,
            0.29512975348083603
          ],
          [
            -1.2174657897587167,
            -0.278575529594815,
            0.5539420300028517,
            1.1591670680136388,
            -0.98787490201699,
            0.32851770745777337
          ],
          [
            -1.3176267759094336,
            -0.3475308753523738,
            0.5538918128649598,
            1.0826122792384552,
            -1.0067604730815702,
            0.361903283681766
          ],
          [
            -1.3992783600345409,
            -0.4218541391424231,
            0.48884362307436224,
            1.000599648845798,
            -1.0299730426521976,
            0.3928410320680725
          ],
          [
            -1.457325859234656,
            -0.49987351618156844,
            0.3396168177064912,
            0.9144098441387274,
            -1.0577950238221612,
            0.4166919119297223
          ],
          [
            -1.4665394092173507,
            -0.5857136480190397,
            0.14298497398143648,
            0.8262652799876182,
            -1.0905923316973647,
            0.42976545144797446
          ],
          [
            -1.4015792867139871,
            -0.6197346943357478,
            0.00045655456512900817,
            0.7399113582766653,
            -1.1269578875273873,
            0.43302251930398755
          ],
          [
            -1.2854684446860158,
            -0.5942714260546306,
            6.963787913266632e-05,
            0.6590863455356557,
            -1.1635115852986029,
            0.4330354836912731
          ],
          [
            -1.1569322201597614,
            -0.5348572441677483,
            3.458394261356994e-05,
            0.5856496744013832,
            -1.1974615713064347,
            0.43303836243836447
          ],
          [
            -1.0283880404207046,
            -0.4754320301231029,
            2.2205032763440617e-05,
            0.5199604524152757,
            -1.2278301714830941,
            0.4330399812845472
          ],
          [
            -0.8998415831975519,
            -0.41600462939820654,
            1.5382457345245113e-05,
            0.4620189800661735,
            -1.25461699803629,
            0.4330410630162034
          ],
          [
            -0.7712940136550728,
            -0.3565762971278377,
            1.0904009994639747e-05,
            0.41182535783341245,
            -1.27782195830579,
            0.43304182170511785
          ],
          [
            -0.6427457842575747,
            -0.297147450035856,
            7.701759777455742e-06,
            0.36937963845797134,
            -1.2974450090886782,
            0.43304235846910416
          ],
          [
            -0.5141971181975327,
            -0.23771828041328655,
            5.302292836324593e-06,
            0.3346818546496757,
            -1.3134861253084054,
            0.43304273242098806
          ],
          [
            -0.3856481413795975,
            -0.17828889468507564,
            3.456019602679533e-06,
            0.3077320287406084,
            -1.3259452908117988,
            0.43304298255857854
          ],
          [
            -0.25709893138873013,
            -0.11885935883373781,
            2.015191162856782e-06,
            0.28853017700274525,
            -1.3348224946082043,
            0.4330431366668835
          ],
          [
            -0.12854953919671028,
            -0.05942971694667301,
            8.848241260637256e-07,
            0.2770763118745743,
            -1.3401177290082336,
            0.43304321561041204
          ],
          [
            0,
            0,
            0,
            0.2733704432225537,
            -1.3418309885764041,
            0.4330432356596339
          ]
        ],
        "controls": [
          [
            5.6143341107319085e-06,
            0.31999277301334206,
            7.038968958455736e-07
          ],
          [
            1.0055354577554078e-05,
            0.39537340091294143,
            1.8895983917424162e-06
          ],
          [
            2.0744629883729773e-05,
            0.46991905563881037,
            4.142444222362836e-06
          ],
          [
            0.00012039059798049694,
            0.5435559680844907,
            7.974615197492766e-06
          ],
          [
            0.060003690713047744,
            0.5566003659748128,
            1.2077951191964877e-05
          ],
          [
            0.14553026613436365,
            0.5432881028131524,
            1.4869876044912283e-05
          ],
          [
            0.24778137907127215,
            0.512716606657092,
            1.6669522426984386e-05
          ],
          [
            0.37218582058279415,
            0.4596474304117941,
            1.7864201136736986e-05
          ],
          [
            0.47938603549078623,
            0.42363401907975706,
            1.8481017232775463e-05
          ],
          [
            0.5552482023751419,
            0.4189595491322483,
            1.7991100632329673e-05
          ],
          [
            0.6083610664400583,
            0.3916308599191309,
            4.330312208911809e-07
          ],
          [
            0.6485436493457092,
            0.35144554589957283,
            -3.152585938265478e-06
          ],
          [
            0.6886418882779131,
            0.31133795928648295,
            -1.0950682311951693e-05
          ],
          [
            0.7286215721186873,
            0.2713346238160838,
            -2.0820307141775914e-05
          ],
          [
            0.6932515897784914,
            0.15624594185330276,
            -2.385096316847729e-05
          ],
          [
            0.588688993509805,
            -0.02761872679951658,
            -2.482686288785898e-05
          ],
          [
            0.5886733968932754,
            -0.10622527349068743,
            -2.515516015567245e-05
          ],
          [
            0.5886704906287846,
            -0.18395561036780905,
            -2.518341566325334e-05
          ],
          [
            0.8718746514064176,
            0.08152792231138663,
            -0.014435569045766832
          ],
          [
            0.7528381652831723,
            0.03366715183554607,
            -0.018428907223210562
          ],
          [
            0.5345302090720709,
            -0.09933821006302955,
            0.007199424479165203
          ],
          [
            0.4398779683099876,
            -0.09135583693672017,
            -0.0005781409925525932
          ],
          [
            0.34069853007925044,
            -0.06199563857556532,
            -0.0005760880074212291
          ],
          [
            0.22533061720249173,
            -0.016253097833706754,
            -0.0005727269568917801
          ],
          [
            0.15291729231860188,
            -0.013409576958244613,
            -0.0005690353733236858
          ],
          [
            0.08310841087596717,
            -0.013182173892935816,
            -0.0005647392484239208
          ],
          [
            0.013308004668591148,
            -0.012977870081878985,
            -0.0005590711721610488
          ],
          [
            -0.05648801942887,
            -0.012790665530269054,
            -0.000549867266167574
          ],
          [
            -0.12626426262436521,
            -0.012619372181878268,
            -0.000519630772786396
          ],
          [
            -0.12085565180194527,
            -0.012464232879791454,
            0.07470460759619285
          ],
          [
            -0.19531640846812476,
            -0.013215387282122695,
            0.102952044180752
          ],
          [
            -0.31048377469705013,
            -0.01391962533165259,
            0.08497795838496926
          ],
          [
            -0.3837870210607693,
            -0.012886019055167845,
            0.08497861196795652
          ],
          [
            -0.457023460918699,
            -0.00972023141877925,
            0.08497941153173263
          ],
          [
            -0.5301322685479716,
            -0.004447690223782854,
            0.08497999156696401
          ],
          [
            -0.603051902926952,
            0.0029044970146569695,
            0.08498031613275117
          ],
          [
            -0.6757212514391284,
            0.012307544975381671,
            0.08498031604341082
          ],
          [
            -0.7480794747217264,
            0.023730728595221868,
            0.08497981642719306
          ],
          [
            -0.8200646301704589,
            0.03714009133971669,
            0.08497838541659856
          ],
          [
            -0.8770567760832579,
            0.037942647826691565,
            0.08497395676860615
          ],
          [
            -0.9039932257663852,
            0.011014147286906244,
            0.08496407811949969
          ],
          [
            -0.929905922566299,
            -7.866499330716407e-06,
            0.07004890983869679
          ],
          [
            -0.9376703361666097,
            -0.02151798916801143,
            0.04076381480685229
          ],
          [
            -0.8884863246186749,
            -0.090807672815327,
            0.006999706862661159
          ],
          [
            -0.7107462356971902,
            -0.0874366116385379,
            -0.010755163091362919
          ],
          [
            -0.5264843392451789,
            -0.04440547100528669,
            -1.870423688145878e-05
          ],
          [
            -0.40905612553092735,
            -1.5620064404158164e-05,
            2.642844816233059e-06
          ],
          [
            -0.3361359482238054,
            -3.804540266147751e-06,
            2.4660949872541464e-06
          ],
          [
            -0.2632297023651599,
            -1.759665578520279e-06,
            1.8415110628475214e-06
          ],
          [
            -0.19032549975175211,
            -9.2216588458197e-07,
            1.3325493195522346e-06
          ],
          [
            -0.11742189927808448,
            -4.812920810356642e-07,
            9.38247662370158e-07
          ],
          [
            -0.0445185193549927,
            -2.2958725597111147e-07,
            6.311379121502874e-07
          ],
          [
            0.028384775139541383,
            -8.408469090936142e-08,
            3.899323448297141e-07
          ],
          [
            0.10128803983390343,
            -1.8254655371928702e-09,
            1.997009566662147e-07
          ],
          [
            0.17419129956541568,
            4.3005106893516376e-08,
            4.988074619998805e-08
          ],
          [
            0.24709456577978542,
            6.722564993540607e-08,
            -6.720342324695804e-08
          ]
        ],
        "waypoint_times": [
          0,
          1.1351121953192422,
          1.8234938254722028,
          3.390578546649335
        ],
        "totalTime": 3.390578546649335
      },
      "followsTrajectoryId": null
    },
    {
      "id": "f58affb2-cdfb-4878-9b85-a13a6f4ef2e5",
      "name": "Trajectory 2",
      "waypoints": [
        {
          "x": 0.2733704432225537,
          "y": -1.3418309885764041,
          "heading": 0.4330432356596339,
          "stop": true,
          "v_max": 3,
          "omega_max": 10,
          "type": "constrained",
          "intake_x": 0.760775,
          "intake_y": -1.5372,
          "intake_distance": 0.5,
          "intake_velocity_max": 1,
          "intake_velocity_slack": 0.1
        },
        {
          "x": 0.791475,
          "y": -0.3294,
          "heading": 0,
          "stop": false,
          "v_max": 3,
          "omega_max": 10,
          "type": "constrained",
          "intake_x": 1.437875,
          "intake_y": -0.324825,
          "intake_distance": 0.5,
          "intake_velocity_max": 1,
          "intake_velocity_slack": 0.1
        },
        {
          "x": 1.5159838435515862,
          "y": -0.34648747419477505,
          "heading": -0.07997488285147353,
          "stop": false,
          "v_max": 3,
          "omega_max": 10,
          "type": "constrained",
          "intake_x": 2.02805,
          "intake_y": -0.32025,
          "intake_distance": 0.5,
          "intake_velocity_max": 1,
          "intake_velocity_slack": 0.1
        },
        {
          "x": 0.27208939607934207,
          "y": -1.3777098977836064,
          "heading": 0.5338144175782022,
          "stop": true,
          "v_max": 3,
          "omega_max": 10,
          "type": "constrained",
          "intake_x": 0.6692750000000001,
          "intake_y": -1.450275,
          "intake_distance": 0.5,
          "intake_velocity_max": 1,
          "intake_velocity_slack": 0.1
        }
      ],
      "constraints": [
        {
          "id": "ea7cd39c-6fb0-4aaa-8d81-1c56171009d8",
          "type": "heading-tangent",
          "fromWaypoint": 1,
          "toWaypoint": 2,
          "params": {},
          "enabled": true
        },
        {
          "id": "ace4b41b-39ee-4d43-8318-c360c2eefb2b",
          "type": "stay-in-rect",
          "fromWaypoint": 0,
          "toWaypoint": 3,
          "params": {
            "x": 0.25,
            "y": -1.83,
            "width": 3.66,
            "height": 3.66
          },
          "enabled": true
        },
        {
          "id": "f25403a1-1b89-488a-b13c-55d0bb7feda1",
          "type": "max-omega",
          "fromWaypoint": 1,
          "toWaypoint": 2,
          "params": {
            "omega_max": 0.1
          },
          "enabled": true
        }
      ],
      "eventMarkers": [],
      "solverSettings": {
        "samplesPerMeter": 20,
        "minSamplesPerSegment": 8,
        "controlEffortWeight": 0.03
      },
      "trajectory": {
        "times": [
          0,
          0.06346998191330971,
          0.12693996382661943,
          0.19040994573992914,
          0.25387992765323886,
          0.31734990956654857,
          0.3808198914798583,
          0.444289873393168,
          0.5077598553064777,
          0.5712298372197875,
          0.6346998191330973,
          0.698169801046407,
          0.7616397829597168,
          0.8251097648730266,
          0.8885797467863363,
          0.9520497286996461,
          1.0155197106129559,
          1.0789896925262656,
          1.1424596744395754,
          1.2059296563528852,
          1.269399638266195,
          1.3328696201795047,
          1.3963396020928145,
          1.4598095840061243,
          1.5131274929680194,
          1.5664454019299145,
          1.6197633108918097,
          1.6730812198537048,
          1.7263991288156,
          1.7797170377774951,
          1.8330349467393903,
          1.8863528557012854,
          1.9396707646631806,
          1.9929886736250757,
          2.046306582586971,
          2.0996244915488664,
          2.152942400510762,
          2.206260309472657,
          2.2595782184345525,
          2.3156345442773607,
          2.371690870120169,
          2.427747195962977,
          2.4838035218057852,
          2.5398598476485934,
          2.5959161734914016,
          2.6519724993342098,
          2.708028825177018,
          2.764085151019826,
          2.8201414768626343,
          2.8761978027054425,
          2.9322541285482506,
          2.988310454391059,
          3.044366780233867,
          3.100423106076675,
          3.1564794319194833,
          3.2125357577622915,
          3.2685920836050997,
          3.324648409447908,
          3.380704735290716,
          3.436761061133524,
          3.4928173869763324,
          3.5488737128191405,
          3.6049300386619487,
          3.660986364504757,
          3.717042690347565,
          3.7730990161903732,
          3.8291553420331814,
          3.8852116678759896,
          3.9412679937187978,
          3.997324319561606,
          4.053380645404414,
          4.109436971247222
        ],
        "states": [
          [
            0,
            0,
            1.811977972786976e-28,
            0.2733704432225537,
            -1.3418309885764041,
            0.4330432356596339
          ],
          [
            -0.03509877673444765,
            0.12394501111129651,
            -1.255945412717948e-05,
            0.27220194999468683,
            -1.3377097052999938,
            0.43304272903252955
          ],
          [
            -0.05549016091012181,
            0.24147230659028399,
            -2.055702959598163e-05,
            0.269294173434461,
            -1.3259353680964894,
            0.43304160928371693
          ],
          [
            -0.06465994849309589,
            0.35395141843588257,
            -2.6996732138018136e-05,
            0.2654648313565646,
            -1.3068696895715843,
            0.433040044776231
          ],
          [
            -0.06523628810064519,
            0.46241705528176447,
            -3.280329291243147e-05,
            0.26133887971981057,
            -1.2807986114250782,
            0.43303809708513197
          ],
          [
            -0.0591921961077974,
            0.5676482900954646,
            -3.843581921374195e-05,
            0.25739622220551656,
            -1.247950917858697,
            0.4330357878758151
          ],
          [
            -0.04799892040247712,
            0.6702286273708835,
            -4.421542425066489e-05,
            0.25400819838526545,
            -1.2085124598856851,
            0.4330331152408121
          ],
          [
            -0.03273983229380663,
            0.7705907128920985,
            -5.044291109584755e-05,
            0.25146564870207616,
            -1.162637078751591,
            0.4330300577109997
          ],
          [
            -0.014190718878108409,
            0.869048065603817,
            -5.747298512450964e-05,
            0.2500008665292166,
            -1.1104551239396487,
            0.43302657255111726
          ],
          [
            0.02021427666144028,
            0.9610489570003176,
            -6.558750269506555e-05,
            0.25023996020936173,
            -1.052239133851699,
            0.4330225974515006
          ],
          [
            0.08559519848299485,
            1.0411893606327367,
            -7.44867942636482e-05,
            0.2536914112329669,
            -0.9885789452164817,
            0.4330180756695704
          ],
          [
            0.1788516633049402,
            1.0924157513429593,
            -3.796996402105528e-05,
            0.2622187821994513,
            -0.9207941798748216,
            0.43301482106459305
          ],
          [
            0.3035007636393427,
            1.1118436162680396,
            -5.9584558291069276e-05,
            0.2777081750029618,
            -0.850815994619485,
            0.43301153924394126
          ],
          [
            0.41895197132115597,
            1.1146987046770978,
            -0.059650356773947324,
            0.3008023859810808,
            -0.7801541798388912,
            0.4306039352350006
          ],
          [
            0.5054053778347604,
            1.0926046852273776,
            -0.39034711838649866,
            0.3302494695107579,
            -0.7101296857773669,
            0.41347799913643674
          ],
          [
            0.5842661599169983,
            1.0482276340344248,
            -0.745980728539228,
            0.36490495651821714,
            -0.6422200142032615,
            0.3743568206017928
          ],
          [
            0.6857709757802136,
            0.995601590248191,
            -0.794708115381401,
            0.4052998813791538,
            -0.5773673568625811,
            0.3250438297121202
          ],
          [
            0.7879024695531933,
            0.9367100551230918,
            -0.7947348308234552,
            0.4521610301322511,
            -0.5160517830134795,
            0.2746026419641769
          ],
          [
            0.8435550880266751,
            0.8008705972244783,
            -0.7947339472013595,
            0.5039908186251387,
            -0.4610384130412505,
            0.22416087190744785
          ],
          [
            0.8787798452443492,
            0.6444294137352976,
            -0.7947220335915448,
            0.558691120879717,
            -0.41533381242067396,
            0.17371960286266364
          ],
          [
            0.9051798752587864,
            0.48765854310666684,
            -0.7946984721897066,
            0.615345449811885,
            -0.37956964389681336,
            0.12327955981310865
          ],
          [
            0.922821930526598,
            0.3310160272508079,
            -0.7946552649792851,
            0.6733957963645892,
            -0.35375222475601115,
            0.07284180465506322
          ],
          [
            0.931794055201346,
            0.17495675515065262,
            -0.7944971088821562,
            0.7322890639604631,
            -0.337858896084649,
            0.02241142854443708
          ],
          [
            0.9328713562979202,
            0.09376229060975316,
            -0.09999831620797028,
            0.791475,
            -0.3294,
            2.6374581827406817e-31
          ],
          [
            1.0600005303979818,
            0.09197263351862454,
            -0.09999771474183727,
            0.8447323141969901,
            -0.3244416714751203,
            -0.005331681805717109
          ],
          [
            1.1871031382479067,
            0.08940176902442956,
            -0.09999771854063932,
            0.9047671865221356,
            -0.3195996687348219,
            -0.010663350979934021
          ],
          [
            1.2940086613696802,
            0.08604471937846217,
            -0.09999772070876074,
            0.9710198704949596,
            -0.3149163356259894,
            -0.015995020304327916
          ],
          [
            1.3307250869419325,
            0.05943892860922354,
            -0.09999772126497462,
            1.0410302664709876,
            -0.3110579631037989,
            -0.021326689692560585
          ],
          [
            1.2991352187493106,
            0.008071092133434802,
            -0.09999772317976921,
            1.1111083077565937,
            -0.309306471062163,
            -0.026658359154079027
          ],
          [
            1.2250176920034364,
            -0.04518680207254386,
            -0.09999772811271332,
            1.178325160686827,
            -0.31034760094352415,
            -0.03199002881461107
          ],
          [
            1.1324148474234212,
            -0.07815589836367737,
            -0.09999773687768998,
            1.2410783035937494,
            -0.31366671096256915,
            -0.03732169886121197
          ],
          [
            1.0209334592141641,
            -0.090136864946079,
            -0.09999775145207138,
            1.298371134496453,
            -0.31816278014188965,
            -0.042653369561693286
          ],
          [
            0.8940142244931703,
            -0.08460299519348725,
            -0.09999777275532237,
            1.3492923099616974,
            -0.3228130943003531,
            -0.047985041255319556
          ],
          [
            0.7670694427052214,
            -0.07829789334587828,
            -0.09999779771653294,
            1.3934456591468556,
            -0.32714772608729825,
            -0.0533167142022381
          ],
          [
            0.6401593117291493,
            -0.07127713021510416,
            -0.09999782571605545,
            1.4308314831651847,
            -0.33112709442356836,
            -0.05864838857758284
          ],
          [
            0.5132909399513826,
            -0.063538126600778,
            -0.09999785313239187,
            1.4614518220082802,
            -0.3347129698289734,
            -0.06398006442705223
          ],
          [
            0.38646931985242444,
            -0.055076013858244684,
            -0.09999781654022148,
            1.4853090360335752,
            -0.33786692183622863,
            -0.0693117396827813
          ],
          [
            0.2596990234901769,
            -0.04588546327662753,
            -0.0999968720508573,
            1.5024057401155562,
            -0.34055024761038,
            -0.07464338383211676
          ],
          [
            0.24988547908896488,
            -0.17181620912290804,
            -0.09999297636111226,
            1.5159838435515862,
            -0.34648747419477505,
            -0.07997488285147353
          ],
          [
            0.24915627712941524,
            -0.18728403170858038,
            1.0687364291226231,
            1.5299657738407317,
            -0.35657529163329077,
            -0.04559040083296232
          ],
          [
            0.19785012498489998,
            -0.26404366362561,
            1.0690126384784189,
            1.5423994767069802,
            -0.36931737402330694,
            0.01432848776752088
          ],
          [
            0.1085044022742772,
            -0.30395716678058515,
            1.0690273729819324,
            1.5508546390806357,
            -0.3852699129792353,
            0.07425391262437546
          ],
          [
            -0.013218106322352098,
            -0.32109245144885157,
            1.0690338366354266,
            1.5533618063332346,
            -0.4027772813820652,
            0.13417988043346796
          ],
          [
            -0.14259809571246357,
            -0.33995664205891857,
            1.0690371586133776,
            1.5488205557369108,
            -0.4212841028621717,
            0.19410610306959675
          ],
          [
            -0.2704510162632557,
            -0.3676570356491324,
            1.0690382953501367,
            1.5370670665769934,
            -0.441097348935386,
            0.25403243715121027
          ],
          [
            -0.39620363221194893,
            -0.40416269929864646,
            1.0690370670005254,
            1.5182030206973331,
            -0.4627117490940733,
            0.3139587540315895
          ],
          [
            -0.5192842476357831,
            -0.4493984268194716,
            1.0690322929464282,
            1.4923622075417067,
            -0.48661905091408786,
            0.37388488074138493
          ],
          [
            -0.639119744191288,
            -0.5032481534988139,
            1.0690206084269611,
            1.4597105267816652,
            -0.513305638674671,
            0.43381050340136507
          ],
          [
            -0.7551376654889432,
            -0.5655542452783753,
            1.0689906761485102,
            1.420446011006461,
            -0.5432502216431876,
            0.4937348467288598
          ],
          [
            -0.8604123825775597,
            -0.6320882849591613,
            0.9922905393886704,
            1.374986757510333,
            -0.5768080753754371,
            0.5510341333280074
          ],
          [
            -0.9568466349208161,
            -0.7017632267985018,
            0.854769597367461,
            1.3238842877165105,
            -0.6141910196224831,
            0.6019528227321228
          ],
          [
            -1.0475800346935502,
            -0.7742598779707051,
            0.6851278986800023,
            1.2675470824298394,
            -0.6555709893299514,
            0.6440635365786372
          ],
          [
            -1.1314260432548313,
            -0.8488858939645864,
            0.49413819242798473,
            1.206333147928742,
            -0.7010905822023683,
            0.6759343093207817
          ],
          [
            -1.2017515751289263,
            -0.924684421253279,
            0.2831893456185744,
            1.1408258387862196,
            -0.7508459184323331,
            0.6964159710023144
          ],
          [
            -1.2613327756056356,
            -0.9957979235219591,
            0.10003567876581589,
            1.071704834901147,
            -0.8047327520695928,
            0.7060236660132244
          ],
          [
            -1.3052250347844294,
            -1.0520605060663488,
            0.014881876874527324,
            0.9997138241482556,
            -0.8621876335150477,
            0.7087176497992295
          ],
          [
            -1.3281321950740013,
            -1.0813126117396143,
            -0.16859585295600898,
            0.9258835524481106,
            -0.9220197079699816,
            0.7032739256249273
          ],
          [
            -1.3280567753788852,
            -1.0604926730799493,
            -0.23300110160465376,
            0.8514474331268383,
            -0.9820430817265752,
            0.691619344491852
          ],
          [
            -1.3018007116683052,
            -0.9886265925993047,
            -0.20973478174688018,
            0.7777767672437073,
            -1.0394113762137513,
            0.6793542482546079
          ],
          [
            -1.2520549682964002,
            -0.8985691591537033,
            -0.20965779217700167,
            0.7062599477799271,
            -1.092217562098578,
            0.6675999207149288
          ],
          [
            -1.1803913914629176,
            -0.8118512623480387,
            -0.20963362809987454,
            0.6381702506182967,
            -1.1400713804200355,
            0.6558481013160166
          ],
          [
            -1.0852578976493394,
            -0.7291313680191539,
            -0.2096168589694757,
            0.5747816685495263,
            -1.1831788988972312,
            0.6440973834010603
          ],
          [
            -0.9791548559486137,
            -0.649065640125591,
            -0.20960211316914007,
            0.5170450167681747,
            -1.221725135861473,
            0.6323475362417621
          ],
          [
            -0.8720776280544957,
            -0.570303732361994,
            -0.20958784531571925,
            0.46528348120171137,
            -1.2558196701221067,
            0.6205984992966562
          ],
          [
            -0.7640532701555186,
            -0.4928651511546257,
            -0.20957323702004674,
            0.41955090225437336,
            -1.285536145542244,
            0.6088502737758129
          ],
          [
            -0.6550916216458638,
            -0.4167718911737404,
            -0.20955758322103143,
            0.37990010654212686,
            -1.310949371864456,
            0.5971029028861886
          ],
          [
            -0.5452008765773103,
            -0.3420462617671588,
            -0.20954001990041485,
            0.34638341746360674,
            -1.332135401095506,
            0.5853564747952553
          ],
          [
            -0.4343892607739249,
            -0.26871066512537933,
            -0.20951920316418637,
            0.3190526984916509,
            -1.34917153873152,
            0.5736111425213473
          ],
          [
            -0.32266550285245515,
            -0.19678756096921599,
            -0.2094925291120894,
            0.2979593376665537,
            -1.3621363479848194,
            0.5618671775244405
          ],
          [
            -0.21003923638896294,
            -0.12629956591003105,
            -0.20945311181909498,
            0.2831542077352335,
            -1.3711096560151586,
            0.5501251437304211
          ],
          [
            -0.09652311342024704,
            -0.0572705571935187,
            -0.20936594233671743,
            0.27468755408321305,
            -1.3761725954124315,
            0.5383869532367942
          ],
          [
            0,
            0,
            0,
            0.27208939607934207,
            -1.3777098977836064,
            0.5338144175782022
          ]
        ],
        "controls": [
          [
            0.04352621261848747,
            0.276470358343402,
            -2.8181693356546114e-06
          ],
          [
            0.07691649039003615,
            0.3189506416268697,
            -3.721187110658287e-06
          ],
          [
            0.11019980239593324,
            0.3608471187070313,
            -4.598462710787753e-06
          ],
          [
            0.14342113155750072,
            0.40217523505206204,
            -5.44425500874066e-06
          ],
          [
            0.17662861298345756,
            0.44293363975136213,
            -6.295939650949344e-06
          ],
          [
            0.20987504582139507,
            0.4831061699334589,
            -7.192980427464864e-06
          ],
          [
            0.24322267144803583,
            0.5226596197688289,
            -8.180079281717912e-06
          ],
          [
            0.2767537200015112,
            0.5615351236582844,
            -9.315474910090676e-06
          ],
          [
            0.3319198326666998,
            0.5783002659274039,
            -1.0637233262746236e-05
          ],
          [
            0.41784449005803925,
            0.5638785859332957,
            -1.2058102929054777e-05
          ],
          [
            0.4941476864396084,
            0.5058450651002353,
            -3.2325178292515723e-06
          ],
          [
            0.5815126109785496,
            0.4184730553799235,
            -1.0674684899209847e-05
          ],
          [
            0.6106148316701969,
            0.37600110424724675,
            -0.013380441715552414
          ],
          [
            0.5832581802782676,
            0.3333837580952018,
            -0.08335398197887242
          ],
          [
            0.5771158199921834,
            0.2832002831611615,
            -0.13967886007959873
          ],
          [
            0.634344487037217,
            0.24027869181178083,
            -0.1253683533479283
          ],
          [
            0.6616498743120439,
            0.216396648248353,
            -0.1219154936914241
          ],
          [
            0.5561081424861913,
            0.06911128074501614,
            -0.1219133990064555
          ],
          [
            0.515026161192786,
            -0.01455864688633335,
            -0.12191078847398439
          ],
          [
            0.5029040419623199,
            -0.071439640737524,
            -0.12190634729643926
          ],
          [
            0.49329420448513994,
            -0.12815789402754915,
            -0.12189832467736963
          ],
          [
            0.4861839567440301,
            -0.18458913600709909,
            -0.12186590348157966
          ],
          [
            0.48155859472008744,
            -0.08487201559002427,
            0.03395825364476369
          ],
          [
            0.8001901089643578,
            0.048274021193026255,
            -0.015339755612316687
          ],
          [
            0.8653303996138033,
            0.050281094492830705,
            -0.015339810696386454
          ],
          [
            0.8796802916957601,
            0.05189687210494811,
            -0.015339810882143989
          ],
          [
            0.7588588126000254,
            -0.006145230744855841,
            -0.015339810822316492
          ],
          [
            0.6076812475639244,
            -0.08260218290205627,
            -0.015339811238392828
          ],
          [
            0.48575039932541664,
            -0.11530656235936954,
            -0.015339812266887144
          ],
          [
            0.4008913727132141,
            -0.09292759387046046,
            -0.015339813956505254
          ],
          [
            0.3048135638312917,
            -0.05922688998373613,
            -0.015339816715352266
          ],
          [
            0.20723834888363696,
            -0.024131884042246036,
            -0.015339820589218
          ],
          [
            0.1418009473202647,
            -0.021449981364016477,
            -0.01533982474768787
          ],
          [
            0.07646767427732591,
            -0.01921684045425945,
            -0.015339829316443676
          ],
          [
            0.01113015396038441,
            -0.017319877702792412,
            -0.015339833469634748
          ],
          [
            -0.05421419396280836,
            -0.01575195390495199,
            -0.015339822092622002
          ],
          [
            -0.11956468100059782,
            -0.014509157821197449,
            -0.015339595454478498
          ],
          [
            0.134996157676712,
            -0.33350485994581497,
            -0.015338732108190969
          ],
          [
            0.1352811429469382,
            -0.12053142758732435,
            0.2620082561167253
          ],
          [
            0.008758083344467945,
            -0.28663576797931817,
            0.16401143081190855
          ],
          [
            -0.1237893424165046,
            -0.2336839615974291,
            0.16399174937335145
          ],
          [
            -0.2568380083826188,
            -0.17924665609934748,
            0.16399204691430314
          ],
          [
            -0.3488069543418478,
            -0.16293868694856972,
            0.16399229289874226
          ],
          [
            -0.4257588089418764,
            -0.15757523833229964,
            0.16399228391631676
          ],
          [
            -0.5022968488628986,
            -0.14821279621511785,
            0.163991897035036
          ],
          [
            -0.578219907558248,
            -0.134907258627624,
            0.16399086717283828
          ],
          [
            -0.653320945056946,
            -0.11773459352522309,
            0.16398849490196055
          ],
          [
            -0.727394979535367,
            -0.09678187364056846,
            0.16398237213076858
          ],
          [
            -0.7820585026758381,
            -0.07214341602235275,
            0.1457834257861938
          ],
          [
            -0.8350697994727447,
            -0.0453284675450712,
            0.11958431597532526
          ],
          [
            -0.8902660793082471,
            -0.01884779803248741,
            0.09086591159693069
          ],
          [
            -0.9401642776274756,
            2.9425985393403888e-05,
            0.05977657389564309
          ],
          [
            -0.9742081982979036,
            1.2303885899337308e-05,
            0.025742012540938317
          ],
          [
            -0.9999064995675953,
            -4.597896832183294e-05,
            -2.1894910670280207e-05
          ],
          [
            -0.9950333872637532,
            -5.899090412464169e-05,
            -0.004861955612935558
          ],
          [
            -0.9503403927318451,
            0.007998589375564306,
            -0.041257569557500706
          ],
          [
            -0.8491853658350098,
            0.05169631876473733,
            -0.041146674241680906
          ],
          [
            -0.7163248399213874,
            0.10482298158231729,
            -0.030221489387939483
          ],
          [
            -0.6123225478874852,
            0.11627428448654596,
            -0.03215538096688198
          ],
          [
            -0.5282319685767348,
            0.0914638318467065,
            -0.032156107060915505
          ],
          [
            -0.4336862016032763,
            0.05658699455374238,
            -0.03215415516893802
          ],
          [
            -0.3521849987940084,
            0.035395328487929624,
            -0.03215206291571814
          ],
          [
            -0.2840876999563707,
            0.02841403443498148,
            -0.03214991430811094
          ],
          [
            -0.21594908269152993,
            0.02223555484982206,
            -0.032147644805950476
          ],
          [
            -0.14775432961569018,
            0.016830199056236905,
            -0.03214515576096971
          ],
          [
            -0.07950881977177307,
            0.01218826115208619,
            -0.03214230129331099
          ],
          [
            -0.011219946591330078,
            0.00830197142633681,
            -0.03213883498127276
          ],
          [
            0.057104305856749873,
            0.005163979894176962,
            -0.032134251655165404
          ],
          [
            0.12545510431113194,
            0.0027670523074259366,
            -0.03212713569508972
          ],
          [
            0.19381776673215093,
            0.001103975695654346,
            -0.032109756793315604
          ],
          [
            0.21253932447614257,
            0.00016750472115838294,
            0.017566871086004562
          ]
        ],
        "waypoint_times": [
          0,
          1.4598095840061243,
          2.2595782184345525,
          4.109436971247222
        ],
        "totalTime": 4.109436971247222
      },
      "followsTrajectoryId": "cfd304e0-9977-48fe-8048-0ec292718a97"
    },
    {
      "id": "2d20ebcb-e5c8-491f-a6a0-e72d5c4febc0",
      "name": "Trajectory 3",
      "waypoints": [
        {
          "x": 0.27208939607934207,
          "y": -1.3777098977836064,
          "heading": 0.5338144175782022,
          "stop": true,
          "v_max": 3,
          "omega_max": 10,
          "type": "constrained",
          "intake_x": 0.7745,
          "intake_y": -1.52805,
          "intake_distance": 0.5,
          "intake_velocity_max": 1,
          "intake_velocity_slack": 0.1
        },
        {
          "x": 1.592981827562134,
          "y": -1.6063561950823189,
          "heading": 0,
          "stop": false,
          "v_max": 3,
          "omega_max": 10,
          "type": "constrained",
          "intake_x": 1.22285,
          "intake_y": 0.324825,
          "intake_distance": 0.5,
          "intake_velocity_max": 1,
          "intake_velocity_slack": 0.1
        },
        {
          "x": 0.27148590977390574,
          "y": -1.3846963482973509,
          "heading": 0,
          "stop": true,
          "v_max": 3,
          "omega_max": 10,
          "type": "constrained",
          "intake_x": 0.888875,
          "intake_y": -1.633275,
          "intake_distance": 0.5,
          "intake_velocity_max": 1,
          "intake_velocity_slack": 0.1
        }
      ],
      "constraints": [],
      "eventMarkers": [],
      "solverSettings": {
        "samplesPerMeter": 20,
        "minSamplesPerSegment": 3,
        "controlEffortWeight": 0
      },
      "trajectory": {
        "times": [
          0,
          0.06201628614387822,
          0.12403257228775644,
          0.18604885843163466,
          0.24806514457551287,
          0.3100814307193911,
          0.3720977168632693,
          0.43411400300714753,
          0.49613028915102575,
          0.558146575294904,
          0.6201628614387822,
          0.6821791475826604,
          0.7441954337265386,
          0.8062117198704168,
          0.8682280060142951,
          0.9302442921581733,
          0.9922605783020515,
          1.0542768644459297,
          1.116293150589808,
          1.1783094367336862,
          1.2403257228775644,
          1.3023420090214426,
          1.3643582951653208,
          1.426374581309199,
          1.4883908674530772,
          1.5504071535969555,
          1.6124234397408337,
          1.674439725884712,
          1.7325490964641792,
          1.7906584670436465,
          1.8487678376231138,
          1.906877208202581,
          1.9649865787820484,
          2.0230959493615157,
          2.081205319940983,
          2.13931469052045,
          2.197424061099917,
          2.255533431679384,
          2.313642802258851,
          2.371752172838318,
          2.4298615434177853,
          2.4879709139972523,
          2.5460802845767194,
          2.6041896551561865,
          2.6622990257356536,
          2.7204083963151207,
          2.7785177668945877,
          2.836627137474055,
          2.894736508053522,
          2.952845878632989,
          3.010955249212456,
          3.069064619791923,
          3.12717399037139,
          3.1852833609508573,
          3.2433927315303244
        ],
        "states": [
          [
            0,
            0,
            -2.9689892289175888e-27,
            0.27208939607934207,
            -1.3777098977836064,
            0.5338144175782022
          ],
          [
            0.013973999969167582,
            -0.024465497116950716,
            -1.1368043682876476,
            0.2725459333127933,
            -1.3785023317244502,
            0.48938528481861543
          ],
          [
            0.07673569072066044,
            -0.15407790865861917,
            -1.136886411168672,
            0.2755063415230657,
            -1.3841990188452253,
            0.4188816934890371
          ],
          [
            0.12851545893601252,
            -0.286879793671608,
            -1.1369053368917217,
            0.2820165852840806,
            -1.3980356868088086,
            0.348375480940713
          ],
          [
            0.2574711466367548,
            -0.2512601906543794,
            -1.1369107670287901,
            0.2941769864245349,
            -1.414606439396867,
            0.2778686221306602
          ],
          [
            0.39543905376152455,
            -0.21557831694118088,
            -1.1369128648853182,
            0.3146228701630224,
            -1.4289486246861365,
            0.20736155679752938
          ],
          [
            0.5360509237072633,
            -0.19132814304418555,
            -1.1369128728763354,
            0.34371192247726845,
            -1.4414330261031485,
            0.1368544430402138
          ],
          [
            0.6784707897063248,
            -0.17878080637335445,
            -1.1369102568357106,
            0.3815823551708035,
            -1.4527774774374587,
            0.06634743134079191
          ],
          [
            0.8218303670604251,
            -0.17814311197975588,
            -1.136902144514063,
            0.42831948671853354,
            -1.4637146508759369,
            -0.004159203314028858
          ],
          [
            0.9634854407609451,
            -0.18940483275146816,
            -1.1197326124105456,
            0.4838970929354452,
            -1.4749844732595032,
            -0.07399462400033163
          ],
          [
            1.0939697175510779,
            -0.21068031827050762,
            -1.0001867758806173,
            0.5479022301538998,
            -1.4872736751581888,
            -0.1387641342546841
          ],
          [
            1.2185590372471735,
            -0.2396284976940024,
            -0.8331510998998412,
            0.6198100502041715,
            -1.5011397690754291,
            -0.1942638349995038
          ],
          [
            1.3394278611257555,
            -0.27410088084351053,
            -0.6408770566969789,
            0.6993225673423471,
            -1.5169976285847384,
            -0.2384182257372209
          ],
          [
            1.4462495834907765,
            -0.3082421678596164,
            -0.3162279687923233,
            0.7858697467553357,
            -1.5350149533245705,
            -0.2654749493329322
          ],
          [
            1.5434591079415723,
            -0.35643562571486354,
            -0.10220137984524247,
            0.8787210904051329,
            -1.5556510442721423,
            -0.27672154367892726
          ],
          [
            1.5441424702776416,
            -0.26508029316974135,
            -0.03270610994169737,
            0.9744643318857658,
            -1.5747795266467237,
            -0.2803436461110895
          ],
          [
            1.514028277908138,
            -0.19971448046412943,
            0.389560327706456,
            1.069251787428215,
            -1.5891091374962742,
            -0.26586873850218323
          ],
          [
            1.4173938668799735,
            -0.13518578196019046,
            0.3897162721452639,
            1.1600184755477896,
            -1.5994410098779943,
            -0.2417035592217687
          ],
          [
            1.2758919872520322,
            -0.10005561896868499,
            0.38973860825662576,
            1.2433362905742291,
            -1.6067158386391294,
            -0.21753393059715365
          ],
          [
            1.1336418755659547,
            -0.06847866153614358,
            0.3897473878618384,
            1.31785520631083,
            -1.6119220793862017,
            -0.19336344659260013
          ],
          [
            0.9907194040979962,
            -0.040504601462565445,
            0.38975125020162266,
            1.3835311415327012,
            -1.6152816814455775,
            -0.16919261028888333
          ],
          [
            0.8472010321804652,
            -0.016182377384250622,
            0.38975257226213744,
            1.4403247377422477,
            -1.6170196553096223,
            -0.14502163373786994
          ],
          [
            0.7031657067163997,
            0.004440633867330514,
            0.3897522541585249,
            1.488201457342104,
            -1.6173639994800766,
            -0.12085063929944241
          ],
          [
            0.5586951484576267,
            0.021318861299934128,
            0.38975061760774854,
            1.5271317472951247,
            -1.6165455957004973,
            -0.09667971611696069
          ],
          [
            0.4138738996078348,
            0.03440871211194631,
            0.3897475950644744,
            1.5570912127984944,
            -1.6147980914369138,
            -0.07250894859545606
          ],
          [
            0.26878932161715,
            0.04366872442730677,
            0.38974253730786734,
            1.5780607922969503,
            -1.6123577723341478,
            -0.04833844806222087
          ],
          [
            0.12353166545089607,
            0.04905970605708063,
            0.3897328673151724,
            1.5900269347069744,
            -1.6094634257082434,
            -0.024168441450152203
          ],
          [
            -0.021804420311591754,
            0.05054489965003556,
            0.3896984940734001,
            1.592981827562134,
            -1.6063561950823189,
            -1.442652339740071e-28
          ],
          [
            -0.07097910302052211,
            0.04996866994690883,
            -0.4905138486323075,
            1.590226662586043,
            -1.6034345295654002,
            -0.008905879516123786
          ],
          [
            -0.20792796948150188,
            0.05297067866056768,
            -0.4905292145675983,
            1.5819545065807152,
            -1.6004642269411706,
            -0.037409881405976425
          ],
          [
            -0.34472533848173975,
            0.06039010511559304,
            -0.49053552945967094,
            1.5657281106660785,
            -1.597190682247198,
            -0.06591445176775766
          ],
          [
            -0.4812385299498281,
            0.07225552448693269,
            -0.490538956681855,
            1.5415601259580438,
            -1.5933563076576118,
            -0.09441928557586617
          ],
          [
            -0.6173324661826208,
            0.08859108588352173,
            -0.49054071157028434,
            1.5094709860467657,
            -1.5887019834537408,
            -0.12292425859308727
          ],
          [
            -0.7528694872784176,
            0.10941629799660697,
            -0.49054102677480615,
            1.4694890521371617,
            -1.5829673214699544,
            -0.15142928198041414
          ],
          [
            -0.8877094812171427,
            0.13474584064587905,
            -0.49053967078339283,
            1.421650759386009,
            -1.575890940355188,
            -0.1799342637801482
          ],
          [
            -1.02171004492984,
            0.16458938620056437,
            -0.49053589254331825,
            1.3660007547500959,
            -1.567210751493068,
            -0.20843907995865835
          ],
          [
            -1.1547266182163138,
            0.19895141553447449,
            -0.490527874393905,
            1.302592026316085,
            -1.556664255419178,
            -0.23694352460658913
          ],
          [
            -1.276954496821597,
            0.24349736492212504,
            -0.490475923916145,
            1.2317775983631314,
            -1.54381536628098,
            -0.2654459285662193
          ],
          [
            -1.3780749424280614,
            0.3009917695115497,
            -0.46695259304276815,
            1.1544963396038577,
            -1.5279853449056742,
            -0.29310398739818533
          ],
          [
            -1.465156721276093,
            0.3592337035201385,
            -0.34060174142433347,
            1.0717641667100755,
            -1.5087858308965998,
            -0.31570929092014527
          ],
          [
            -1.5445641202701823,
            0.41625343520887115,
            -0.1512568869511562,
            0.9842089782891464,
            -1.48622110545893,
            -0.3287144199486073
          ],
          [
            -1.5501621358777795,
            0.34590498746581744,
            -0.05164787152167737,
            0.8942835556787493,
            -1.4641799441289176,
            -0.3339333996484609
          ],
          [
            -1.517816289781452,
            0.29567004987568574,
            0.47986200625041725,
            0.8051841393356026,
            -1.445590339154721,
            -0.31788277273127236
          ],
          [
            -1.4396570900719439,
            0.22436925273918937,
            0.480543778796722,
            0.7193496719860424,
            -1.4305281367823421,
            -0.28997385551111104
          ],
          [
            -1.3078747964470887,
            0.1841925634539692,
            0.48058243028903774,
            0.6396831196747537,
            -1.4186757780669774,
            -0.26204837344409126
          ],
          [
            -1.1751054887180608,
            0.14781727824388352,
            0.48059774261190286,
            0.5677033436303573,
            -1.4090478032468126,
            -0.23412148194991186
          ],
          [
            -1.0414426673153938,
            0.1153025841339703,
            0.4806052425636031,
            0.5034650175259773,
            -1.4014215475139447,
            -0.20619398069871156
          ],
          [
            -0.9069804503174258,
            0.08670623771239776,
            0.48060894314256003,
            0.4470173650870442,
            -1.3955709451277458,
            -0.1782661798175559
          ],
          [
            -0.7718160473643513,
            0.06208387693702998,
            0.48061039795032007,
            0.39840404903958837,
            -1.3912666337194144,
            -0.15033824439716487
          ],
          [
            -0.6360501313554291,
            0.041488743369235165,
            0.4806102919924438,
            0.35766298004410774,
            -1.3882760858190226,
            -0.12241028038405057
          ],
          [
            -0.4997868983038104,
            0.02497145213783791,
            0.4806088692352985,
            0.3248261134808978,
            -1.386363755004778,
            -0.0944823697284204
          ],
          [
            -0.36313404724689924,
            0.012579772096432516,
            0.4806059901497519,
            0.2999192451751652,
            -1.3852912350860114,
            -0.06655459395005271
          ],
          [
            -0.2262027518522162,
            0.004358412635460807,
            0.48060075437443056,
            0.28296180853621183,
            -1.384817431839532,
            -0.0386270699485348
          ],
          [
            -0.08910782135623693,
            0.0003488610137094263,
            0.4805883851876322,
            0.2739666676165254,
            -1.3846987455154343,
            -0.010700105890176587
          ],
          [
            0,
            0,
            0,
            0.27148590977390574,
            -1.3846963482973509,
            0
          ]
        ],
        "controls": [
          [
            1.139586705100296e-06,
            -0.06246965663520981,
            -0.25752866929673135
          ],
          [
            0.0004309592201385487,
            -0.3344759885570747,
            -0.17440619855703207
          ],
          [
            0.003833349071403376,
            -0.40851171293437294,
            -0.17440448567216968
          ],
          [
            0.3123503398097567,
            -0.18080648802429417,
            -0.17440433165262995
          ],
          [
            0.4119630299082494,
            -0.1607471184717961,
            -0.17440440975797958
          ],
          [
            0.49634516789483313,
            -0.15051045441125815,
            -0.17440425813975827
          ],
          [
            0.5799203315244494,
            -0.13521940979727884,
            -0.1744036649241164
          ],
          [
            0.6623805813852085,
            -0.1149867545799564,
            -0.1744020185051888
          ],
          [
            0.7395392065671166,
            -0.08994357778074245,
            -0.17051307128079926
          ],
          [
            0.7947397690833576,
            -0.060568311154864704,
            -0.14468717900555528
          ],
          [
            0.8548876111086903,
            -0.029516949148195318,
            -0.11559043279513477
          ],
          [
            0.9157092164859413,
            3.614821414940904e-05,
            -0.08424945850677852
          ],
          [
            0.9496340942362475,
            0.02559439178568099,
            -0.024766418606802572
          ],
          [
            0.9946493735589526,
            0.005319157967685683,
            -2.485732064585003e-05
          ],
          [
            0.7603086095560968,
            0.23961753398564628,
            6.542002014173314e-05
          ],
          [
            0.698904544762742,
            0.210438764159896,
            0.09064195798900834
          ],
          [
            0.5384820977255278,
            0.1850216233773958,
            0.05979450615738268
          ],
          [
            0.4051007737703131,
            0.1070884758527079,
            0.05978816096091067
          ],
          [
            0.33243975563921796,
            0.09146489579375915,
            0.05978851629921213
          ],
          [
            0.25947124442701314,
            0.07754905564317348,
            0.059788749159864
          ],
          [
            0.18622797581454448,
            0.06532678361804627,
            0.059788766180595254
          ],
          [
            0.11274511883950972,
            0.05478491260809373,
            0.059788597428238485
          ],
          [
            0.039058006809824845,
            0.04590985953973742,
            0.059788249953044305
          ],
          [
            -0.03479818305013415,
            0.03868747047385393,
            0.05978768492443827
          ],
          [
            -0.10878847837397465,
            0.03310299135504066,
            0.05978676020962886
          ],
          [
            -0.1828779183052141,
            0.029141039514231287,
            0.05978493949798287
          ],
          [
            -0.2570283208824653,
            0.02678557136787548,
            0.05977785989728363
          ],
          [
            -0.1259378930903206,
            0.026020627401294894,
            -0.14550380671359295
          ],
          [
            -0.356759000279589,
            0.025398266869808974,
            -0.07524919450266332
          ],
          [
            -0.42797520835993674,
            0.02324801216750485,
            -0.0752494407662078
          ],
          [
            -0.4991120746931647,
            0.019333894032196704,
            -0.07524973601483484
          ],
          [
            -0.5701260581171825,
            0.013676612020618768,
            -0.07524987173252091
          ],
          [
            -0.6409735156044234,
            0.006297711297634109,
            -0.07524980517047442
          ],
          [
            -0.7116112438297689,
            -0.0027803929119790804,
            -0.0752494637651941
          ],
          [
            -0.7819965171735165,
            -0.013534411627381294,
            -0.07524869083455688
          ],
          [
            -0.8520869981949828,
            -0.02594017061787474,
            -0.07524712241050692
          ],
          [
            -0.9033094778094014,
            -0.021449486875274707,
            -0.07523564649439937
          ],
          [
            -0.9302297359905352,
            -1.109256451947195e-05,
            -0.06975365351465893
          ],
          [
            -0.9578174369521881,
            -1.3008953121114102e-05,
            -0.04216357887861184
          ],
          [
            -0.9918502338086852,
            -5.308386729057045e-05,
            -0.00808961895252097
          ],
          [
            -0.780352635873666,
            -0.21960823262589574,
            2.7885465409713157e-05
          ],
          [
            -0.7034257938003362,
            -0.18051951181352724,
            0.11603650640984967
          ],
          [
            -0.5674053821429311,
            -0.1971202638000379,
            0.07377060492569439
          ],
          [
            -0.42320533815205646,
            -0.10123753289346216,
            0.07372520048716748
          ],
          [
            -0.35484907813144123,
            -0.08284168327424829,
            0.0737256865001174
          ],
          [
            -0.28606944856373523,
            -0.06632226285206659,
            0.07372621342483605
          ],
          [
            -0.2169079027577662,
            -0.05166796936096973,
            0.0737264778353696
          ],
          [
            -0.14740952323625867,
            -0.03886830763173832,
            0.07372652174875693
          ],
          [
            -0.07761975943958643,
            -0.027911981768828947,
            0.07372638091501732
          ],
          [
            -0.007583958554294635,
            -0.018786732650485978,
            0.0737260575554333
          ],
          [
            0.06265274617024987,
            -0.011479325358438862,
            0.07372549965556666
          ],
          [
            0.13304541843283332,
            -0.005975552366367114,
            0.07372450836922478
          ],
          [
            0.20354883740173885,
            -0.002260115379841908,
            0.07372204153017427
          ],
          [
            0.162042994173507,
            -0.0003148977077325714,
            -0.038360372095437176
          ]
        ],
        "waypoint_times": [
          0,
          1.674439725884712,
          3.2433927315303244
        ],
        "totalTime": 3.2433927315303244
      },
      "followsTrajectoryId": "f58affb2-cdfb-4878-9b85-a13a6f4ef2e5"
    }
  ]
}