{
  "version": 4,
  "name": "basefarfull (Mirrored)",
  "updatedAt": "2026-02-22T02:42:03.279468Z",
  "fieldSize": 3.66,
  "backgroundImageFilename": "6fb5ea3496da8d70c2dfe3ae7babf07384dd2f611379c1161f142f4677d83275.svg",
  "backgroundSettings": {
    "scale": 1,
    "rotation": 90,
    "opacity": 1,
    "mirrorH": false,
    "mirrorV": false
  },
  "variables": {
    "vars": [
      {
        "name": "intake_start_x",
        "value": 0.7,
        "linkedFrom": null
      },
      {
        "name": "intake_end_x",
        "value": 1.34,
        "linkedFrom": null
      },
      {
        "name": "intake_vel",
        "value": 0.18,
        "linkedFrom": null
      }
    ],
    "linkedFrom": null
  },
  "robotParams": {
    "mass": 20,
    "inertia": 0.5,
    "wheel_radius": 0.052,
    "lx": 0.2159,
    "ly": 0.22,
    "w_max": 45.553093425,
    "t_max": 0.6,
    "f_traction_max": 17,
    "default_intake_distance": 0.5,
    "default_intake_velocity": 1,
    "linkedFrom": null
  },
  "fragments": [],
  "groupNames": [],
  "trajectories": [
    {
      "id": "a49a5935-9fd0-46ef-9b59-7d357ce21b7a",
      "name": "forward",
      "waypoints": [
        {
          "x": 0.86925,
          "y": -0.9882,
          "heading": 1.5401936388661779,
          "stop": true,
          "v_max": 3,
          "omega_max": 10,
          "type": "constrained",
          "intake_x": -0.8202499999999999,
          "intake_y": -1.587525,
          "intake_distance": 0.5,
          "intake_velocity_max": 1,
          "intake_velocity_slack": 0.1
        },
        {
          "x": 0.608475,
          "y": 0.617625,
          "heading": 1.5330783743280325,
          "stop": true,
          "v_max": 3,
          "omega_max": 10,
          "type": "constrained",
          "intake_x": -1.1084749999999999,
          "intake_y": 0.617625,
          "intake_distance": 0.5,
          "intake_velocity_max": 1,
          "intake_velocity_slack": 0.1
        }
      ],
      "constraints": [],
      "eventMarkers": [],
      "solverSettings": {
        "samplesPerMeter": 20,
        "minSamplesPerSegment": 3,
        "controlEffortWeight": 0
      },
      "trajectory": {
        "times": [
          0,
          0.05609513676962144,
          0.11219027353924288,
          0.16828541030886432,
          0.22438054707848576,
          0.28047568384810717,
          0.3365708206177286,
          0.39266595738735,
          0.4487610941569714,
          0.5048562309265928,
          0.5609513676962142,
          0.6170465044658356,
          0.6731416412354571,
          0.7292367780050785,
          0.7853319147746999,
          0.8414270515443213,
          0.8975221883139427,
          0.9536173250835641,
          1.0097124618531856,
          1.065807598622807,
          1.1219027353924285,
          1.1779978721620499,
          1.2340930089316713,
          1.2901881457012927,
          1.3462832824709141,
          1.4023784192405355,
          1.458473556010157,
          1.5145686927797783,
          1.5706638295493998,
          1.6267589663190212,
          1.6828541030886426,
          1.738949239858264,
          1.7950443766278854,
          1.8511395133975068
        ],
        "states": [
          [
            0,
            0,
            -1.96567602787302e-30,
            0.86925,
            -0.9882,
            1.5401936388661779
          ],
          [
            8.66302775357916e-05,
            0.006985472848117333,
            1.7440840138865144,
            0.8692540236886094,
            -0.9880022998354119,
            1.5925691332772878
          ],
          [
            -0.008116349626195687,
            0.13228340955711865,
            1.1514947016843189,
            0.8690764552881283,
            -0.9840609891933851,
            1.6726080865950366
          ],
          [
            -0.024138071711869238,
            0.25012749406197043,
            0.7602429257598898,
            0.8682005759157295,
            -0.9733008967709678,
            1.725451902615216
          ],
          [
            -0.044757543484748946,
            0.3608742584551473,
            0.5019300400470784,
            0.8662846393307956,
            -0.9561316765939313,
            1.760340601175534
          ],
          [
            -0.06787472463700693,
            0.46504700389041453,
            0.3313873055386962,
            0.8631339718385825,
            -0.9329370285277544,
            1.7833749734461397
          ],
          [
            -0.09213189897495022,
            0.5631680660714823,
            0.21879206864574263,
            0.8586494015693958,
            -0.904070890099628,
            1.7985829126624193
          ],
          [
            -0.11665947714338078,
            0.655707338312888,
            0.14445463271892553,
            0.8527932465162847,
            -0.8698592644206942,
            1.8086237026991585
          ],
          [
            -0.14090830149019282,
            0.7430746087008301,
            0.09537550043347781,
            0.8455669722783764,
            -0.8306034938676484,
            1.815253040383231
          ],
          [
            -0.1645394345188034,
            0.8256262916802819,
            0.06297220803499447,
            0.8369965295598517,
            -0.7865834754567845,
            1.8196300591254797
          ],
          [
            -0.18735166825252925,
            0.9036752342630124,
            0.04157849325023514,
            0.8271227398053741,
            -0.7380603815079204,
            1.8225200324761621
          ],
          [
            -0.20923375818374512,
            0.977499699223978,
            0.027453408353688778,
            0.8159950039636163,
            -0.6852788439200251,
            1.8244282021420315
          ],
          [
            -0.23013290307029965,
            1.0473505312997573,
            0.018127117507098264,
            0.803667202563387,
            -0.6284686841557741,
            1.8256881328195178
          ],
          [
            -0.25003393139206503,
            1.1134565495556699,
            0.011968980427312752,
            0.7901950423662801,
            -0.5678462922618221,
            1.8265200447814707
          ],
          [
            -0.26894556126439867,
            1.1760285053128887,
            0.007902391739363784,
            0.775634358190556,
            -0.5036157454386003,
            1.8270693251861139
          ],
          [
            -0.2868913411523607,
            1.2352619684337498,
            0.00521650677902925,
            0.7600400449830658,
            -0.4359697362684785,
            1.8274319527967289
          ],
          [
            -0.3039036903753281,
            1.2913394434079262,
            0.0034419242161534917,
            0.7434654050335284,
            -0.36509036190619726,
            1.8276712820817043
          ],
          [
            -0.3200199914020556,
            1.344431941055077,
            0.0022685707782038496,
            0.7259617678989413,
            -0.2911498107627727,
            1.8278291210592583
          ],
          [
            -0.33528003514541554,
            1.394700163221849,
            0.0014913799042133127,
            0.7075782889017641,
            -0.21431097253592454,
            1.8279330375368725
          ],
          [
            -0.3497243410403231,
            1.4422953931204474,
            0.0009740744834612608,
            0.6883618646174631,
            -0.13472799050351858,
            1.828001161860626
          ],
          [
            -0.363392963649058,
            1.4873600685192507,
            0.0006237281352135119,
            0.6683571277614927,
            -0.05254677312146891,
            1.828045281739
          ],
          [
            -0.37632392625275024,
            1.530027229154877,
            0.0003627444362646685,
            0.6476065186618661,
            0.032094494431814065,
            1.828072432557446
          ],
          [
            -0.32270554752567115,
            1.482610671720023,
            -0.8811983283450129,
            0.6280104707359401,
            0.11658340969675846,
            1.801619172203291
          ],
          [
            -0.2022348409169898,
            1.425342766993466,
            -0.8760944560845819,
            0.6133141269476134,
            0.19815453571109554,
            1.7523415020949265
          ],
          [
            -0.0845371768193196,
            1.3664899743861552,
            -0.8281472582566439,
            0.605298594106328,
            0.27646845471627896,
            1.7046367357394177
          ],
          [
            -0.0006768211988082375,
            1.2666956096363933,
            -0.7442935766006091,
            0.6029362891771944,
            0.3503143291718185,
            1.6606998592478739
          ],
          [
            0.012377169519927836,
            1.0893808906131377,
            -0.6285432774160521,
            0.6032864544939928,
            0.41635353830178484,
            1.6224246339340072
          ],
          [
            0.019107250299176377,
            0.9138756905302926,
            -0.48184021547717637,
            0.6041877249758119,
            0.4724962449070829,
            1.5915719605977523
          ],
          [
            0.020043518696486726,
            0.7403876056020493,
            -0.3181384607347881,
            0.605298880122092,
            0.5188501892576621,
            1.5694590927293555
          ],
          [
            0.01771847054008524,
            0.5750541636520033,
            -0.21004812088437008,
            0.6063660511109564,
            0.555702801303088,
            1.5548590656338768
          ],
          [
            0.014075596648400931,
            0.41853343404545884,
            -0.13867990807462988,
            0.6072626358105583,
            0.5835303994903897,
            1.5452196017311313
          ],
          [
            0.009663278179118879,
            0.27035926028673823,
            -0.09155806877069438,
            0.6079311777545432,
            0.6028141902375818,
            1.5388554198134274
          ],
          [
            0.004842580175434336,
            0.13008437533990852,
            -0.06044385185961488,
            0.608339369046375,
            0.6140097286171795,
            1.5346538290133276
          ],
          [
            0,
            0,
            0,
            0.608475,
            0.617625,
            1.5330783743280325
          ]
        ],
        "controls": [
          [
            0.05546470257761489,
            3.5449655175092397e-06,
            0.944529553938147
          ],
          [
            0.9999716626542658,
            2.9453924210713864e-06,
            2.2974095405740614e-05
          ],
          [
            0.9999835174226792,
            2.5212650172613736e-06,
            1.1281910013657453e-05
          ],
          [
            0.9999870522767856,
            2.3233894978007002e-06,
            7.672133701531844e-06
          ],
          [
            0.999988669926298,
            2.2476560772216875e-06,
            5.841465070678793e-06
          ],
          [
            0.9999895173880641,
            2.245637138433485e-06,
            4.6826035067656785e-06
          ],
          [
            0.999989958138972,
            2.2912952466161185e-06,
            3.8469252977411785e-06
          ],
          [
            0.9999901400979002,
            2.3690174140598594e-06,
            3.188681624312466e-06
          ],
          [
            0.9999901306483,
            2.468745453096916e-06,
            2.6342813812337612e-06
          ],
          [
            0.9999899597124423,
            2.5837170304952734e-06,
            2.1402566854113903e-06
          ],
          [
            0.9999896356208471,
            2.7092286392160854e-06,
            1.6766406636721698e-06
          ],
          [
            0.9999891507146166,
            2.8417692870503406e-06,
            1.2190854179589351e-06
          ],
          [
            0.9999884817864481,
            2.9781675428322377e-06,
            7.441343368642284e-07
          ],
          [
            0.9999875864492636,
            3.1143829615131e-06,
            2.2516047235950345e-07
          ],
          [
            0.9999863941255608,
            3.2432400741881963e-06,
            -3.729560212992759e-07
          ],
          [
            0.9999847869735297,
            3.349362366667903e-06,
            -1.103514714295149e-06
          ],
          [
            0.9999825577618556,
            3.39635853371203e-06,
            -2.0598600585972117e-06
          ],
          [
            0.9999793051437408,
            3.2902418141958024e-06,
            -3.4341227099765214e-06
          ],
          [
            0.9999741193263928,
            2.7571789695968913e-06,
            -5.708970391390456e-06
          ],
          [
            0.9999643045378782,
            8.212776291154626e-07,
            -1.0485096494595082e-05
          ],
          [
            0.9999360872493813,
            -7.84297979114803e-06,
            -2.6561001172408408e-05
          ],
          [
            0.19576675404927638,
            -0.32684847811421813,
            -0.4773531827584467
          ],
          [
            -6.427714108330531e-06,
            -0.8405576362405943,
            -0.1593942899439773
          ],
          [
            -5.484329399289649e-05,
            -0.8646730397241903,
            -0.13525275642444487
          ],
          [
            -0.28393568758642257,
            -0.6090687404161139,
            -0.1069839142519641
          ],
          [
            -0.8779067711863416,
            -0.04780627526315634,
            -0.07427914277461209
          ],
          [
            -0.9347844110342663,
            -0.02899392262591832,
            -0.03621590310554552
          ],
          [
            -0.9914584456830445,
            -0.008523164367946751,
            -1.3720971994417046e-05
          ],
          [
            -0.9999078686656133,
            -8.16302855170134e-05,
            -6.307301443951153e-06
          ],
          [
            -0.999925535264606,
            -6.765962879696529e-05,
            -2.8013807781822403e-06
          ],
          [
            -0.9999389236461032,
            -5.61812806284759e-05,
            -5.175234777421489e-07
          ],
          [
            -0.9999486230675431,
            -4.6553624106120584e-05,
            1.7364622605738793e-06
          ],
          [
            -0.9783673661273888,
            -1.960026788192079e-05,
            0.021611197502254303
          ]
        ],
        "waypoint_times": [
          0,
          1.8511395133975068
        ],
        "totalTime": 1.8511395133975068
      },
      "followsTrajectoryId": null
    },
    {
      "id": "56629481-2539-4cde-aa12-615cc108e599",
      "name": "intake_1",
      "waypoints": [
        {
          "x": 0.407175,
          "y": -1.605825,
          "heading": 0,
          "stop": true,
          "v_max": 3,
          "omega_max": 10,
          "type": "constrained",
          "intake_x": -1.355525,
          "intake_y": -0.965325,
          "intake_distance": 0.5,
          "intake_velocity_max": 1,
          "intake_velocity_slack": 0.1
        },
        {
          "x": 0.7,
          "y": -0.9192700046539306,
          "heading": 0,
          "stop": true,
          "v_max": 3,
          "omega_max": 10,
          "type": "constrained",
          "intake_x": -1.08885,
          "intake_y": -0.928725,
          "intake_distance": 0.2,
          "intake_velocity_max": 0.2,
          "intake_velocity_slack": 0.1
        },
        {
          "x": 1.34,
          "y": -0.9192700046539306,
          "heading": 0,
          "stop": true,
          "v_max": 3,
          "omega_max": 10,
          "type": "constrained",
          "intake_x": -1.9457,
          "intake_y": -0.94245,
          "intake_distance": 0.5,
          "intake_velocity_max": 1,
          "intake_velocity_slack": 0.1
        },
        {
          "x": 0.425475,
          "y": -1.4091,
          "heading": 1.5049575574922025,
          "stop": true,
          "v_max": 3,
          "omega_max": 10,
          "type": "constrained",
          "intake_x": -0.769925,
          "intake_y": 0.3294,
          "intake_distance": 0.5,
          "intake_velocity_max": 1,
          "intake_velocity_slack": 0.1
        }
      ],
      "constraints": [
        {
          "id": "406ecbb7-88c8-4abc-be01-ca37e0df41d7",
          "type": "max-velocity",
          "fromWaypoint": 1,
          "toWaypoint": 2,
          "params": {
            "v_max": 0.18
          },
          "enabled": true
        },
        {
          "id": "9b39877e-20c8-48b9-ae31-9b4971dd3a26",
          "type": "circle-obstacle",
          "fromWaypoint": 0,
          "toWaypoint": 3,
          "params": {
            "cx": 1.120875,
            "cy": -0.2562,
            "radius": 0.5
          },
          "enabled": true
        },
        {
          "id": "7e608e3c-76de-4a2d-85da-3a000f7c8032",
          "type": "heading-tangent",
          "fromWaypoint": 1,
          "toWaypoint": 2,
          "params": {},
          "enabled": true
        }
      ],
      "eventMarkers": [
        {
          "waypointIndex": 2,
          "percentage": 0.9,
          "name": "shoot",
          "timestamp": 6.527486544325646
        }
      ],
      "solverSettings": {
        "samplesPerMeter": 20,
        "minSamplesPerSegment": 3,
        "controlEffortWeight": 0.02
      },
      "trajectory": {
        "times": [
          0,
          0.09115381470663983,
          0.18230762941327966,
          0.27346144411991946,
          0.3646152588265593,
          0.4557690735331992,
          0.546922888239839,
          0.6380767029464789,
          0.7292305176531187,
          0.8203843323597586,
          0.9115381470663985,
          1.0026919617730383,
          1.093845776479678,
          1.1849995911863178,
          1.2761534058929576,
          1.3673072205995973,
          1.663603555390255,
          1.9598998901809128,
          2.2561962249715704,
          2.552492559762228,
          2.848788894552886,
          3.1450852293435436,
          3.4413815641342014,
          3.737677898924859,
          4.033974233715517,
          4.330270568506174,
          4.6265669032968315,
          4.922863238087489,
          5.219159572878146,
          5.297507732140515,
          5.375855891402884,
          5.454204050665252,
          5.532552209927621,
          5.61090036918999,
          5.689248528452358,
          5.767596687714727,
          5.845944846977096,
          5.9242930062394645,
          6.002641165501833,
          6.080989324764202,
          6.159337484026571,
          6.237685643288939,
          6.316033802551308,
          6.394381961813677,
          6.4727301210760455,
          6.551078280338414,
          6.629426439600783,
          6.707774598863152,
          6.78612275812552,
          6.864470917387889
        ],
        "states": [
          [
            0,
            0,
            -2.0277910272268817e-29,
            0.407175,
            -1.605825,
            0
          ],
          [
            0.04805123806766212,
            0.15220562857665496,
            -5.73520717768365e-06,
            0.4093974635787353,
            -1.5987693420041724,
            -2.9285410807489143e-07
          ],
          [
            0.09423405283261022,
            0.2873865307885258,
            -6.814145406644695e-06,
            0.4159135621881767,
            -1.5786287599579,
            -8.707328089663235e-07
          ],
          [
            0.13914694712341344,
            0.4067640729475213,
            -6.206211423851504e-06,
            0.42658066421703034,
            -1.5468985049596589,
            -1.4608248202208074e-06
          ],
          [
            0.18340372335867886,
            0.5113749457113399,
            -5.030055475345035e-06,
            0.44131140125568763,
            -1.5049710566838945,
            -1.9664866148794147e-06
          ],
          [
            0.227640995464402,
            0.6020803831429323,
            -3.69692158057818e-06,
            0.46007541031245225,
            -1.4541525299527722,
            -2.356921853685634e-06
          ],
          [
            0.27252620018436685,
            0.6795733381798077,
            -2.334840348196018e-06,
            0.4829017837677589,
            -1.3956783356643487,
            -2.6243590540708794e-06
          ],
          [
            0.3187661519086311,
            0.7443836669919434,
            -9.31743989215778e-07,
            0.5098822746926555,
            -1.3307282799409101,
            -2.765543532845527e-06
          ],
          [
            0.3671160003582132,
            0.7968811354165074,
            8.408820288210624e-07,
            0.5411753006008565,
            -1.260441291667017,
            -2.759962682397088e-06
          ],
          [
            0.416683069446187,
            0.8355830078469405,
            0.0025404528677175093,
            0.5769319849339912,
            -1.1860085385054115,
            0.00012699612515998382
          ],
          [
            0.4078001306133443,
            0.8004161106149453,
            -0.0026455140772123774,
            0.6145033899508916,
            -1.1114721654940924,
            9.375945942613484e-05
          ],
          [
            0.3403266088689567,
            0.6909403604279405,
            7.191624864245715e-05,
            0.6485551886977315,
            -1.0435860805677235,
            -8.63050340704774e-06
          ],
          [
            0.2211528530367138,
            0.5133809147651885,
            3.7823032575087125e-05,
            0.6740652327379838,
            -0.9888351892495001,
            -3.8161662292424126e-06
          ],
          [
            0.12468418201669605,
            0.3405989931943287,
            1.8011479168950314e-05,
            0.6897622912056953,
            -0.9500480533206719,
            -1.3801033129645646e-06
          ],
          [
            0.05089374923035874,
            0.17026153282654682,
            7.218692473413107e-06,
            0.6977147766368096,
            -0.9268973339626188,
            -2.8940435115032415e-07
          ],
          [
            0,
            0,
            8.138443038744893e-30,
            0.7,
            -0.9192700046539306,
            0
          ],
          [
            0.17999997624550784,
            -8.258680247416418e-08,
            -1.3482379930409288e-07,
            0.7279613256627612,
            -0.9192700176648728,
            -5.043485318267926e-08
          ],
          [
            0.17999997668849996,
            -7.256523746858752e-08,
            -1.116360319511159e-07,
            0.7812946589555254,
            -0.9192700405027439,
            -8.170857856981684e-08
          ],
          [
            0.17999997668850617,
            -6.011824649098739e-08,
            -6.774550608712704e-08,
            0.8346279923107327,
            -0.9192700599982366,
            -9.836736891699616e-08
          ],
          [
            0.17999997668851184,
            -4.610466424938842e-08,
            -1.5316417446739503e-08,
            0.8879613256659418,
            -0.9192700755785247,
            -9.882745377609581e-08
          ],
          [
            0.17999997668851653,
            -3.052867848917044e-08,
            3.2359234915417445e-08,
            0.9412946590211525,
            -0.919270086786322,
            -8.553115682374823e-08
          ],
          [
            0.1799999766885197,
            -1.353916588216838e-08,
            6.700033383249966e-08,
            0.9946279923763643,
            -0.919270093181399,
            -6.298470056620431e-08
          ],
          [
            0.1799999766885209,
            4.5905502409337995e-09,
            8.292795626586052e-08,
            1.0479613257315767,
            -0.9192700943829543,
            -3.7174545663987146e-08
          ],
          [
            0.17999997668851983,
            2.343957421811676e-08,
            7.77030450086959e-08,
            1.1012946590867891,
            -0.9192700901111454,
            -1.4557828276196005e-08
          ],
          [
            0.17999997668851633,
            4.247578211149751e-08,
            5.325133891610294e-08,
            1.1546279924420009,
            -0.9192700802263595,
            -6.81588563367086e-10
          ],
          [
            0.17999997668851053,
            6.112903424954686e-08,
            1.7543888740637078e-08,
            1.2079613257972113,
            -0.919270064752344,
            1.7391528217558516e-09
          ],
          [
            0.17999997668850282,
            7.894345435350651e-08,
            -1.5365107772498756e-08,
            1.2612946591524197,
            -0.9192700438663206,
            -5.373250733242685e-09
          ],
          [
            0.17999997624550848,
            9.49699876190168e-08,
            1.4101068435121153e-08,
            1.3146279924388118,
            -0.9192700179556405,
            1.0968173036474127e-09
          ],
          [
            -1.9828895230259127e-29,
            5.069230830574873e-29,
            0,
            1.34,
            -0.9192700046539306,
            0
          ],
          [
            -0.06274153767636552,
            -0.024450847064115117,
            1.2001515109381147,
            1.3375037044950064,
            -0.9202235113444224,
            0.051777553382979846
          ],
          [
            -0.15203057856973018,
            -0.04508195819039785,
            1.5725367714890721,
            1.329029267399803,
            -0.9228892578002219,
            0.16187285144334096
          ],
          [
            -0.2684835802151816,
            -0.07060597373164562,
            1.4732607581520512,
            1.312474145802478,
            -0.9273282858949535,
            0.28079519611599846
          ],
          [
            -0.39251070074571004,
            -0.1155807021365429,
            1.1239493831111889,
            1.286482730609864,
            -0.9345414767589799,
            0.3811522938028622
          ],
          [
            -0.5137987820526195,
            -0.17485254785553148,
            0.75762828159389,
            1.250883088093403,
            -0.9458698718062178,
            0.45340764588005067
          ],
          [
            -0.6263167015247513,
            -0.24113000394186954,
            0.4824647957636949,
            1.206136659924175,
            -0.9621465411451762,
            0.5008951826144403
          ],
          [
            -0.7269272159278022,
            -0.30821003848391615,
            0.33452808897180486,
            1.153055144535395,
            -0.9836665001239131,
            0.5323130497914383
          ],
          [
            -0.8135018028841061,
            -0.37194750809804444,
            0.3187764449753869,
            1.0926515857711872,
            -1.0103176821593731,
            0.5578431442495204
          ],
          [
            -0.8838867002427268,
            -0.4301030300214985,
            0.4303305907438673,
            1.0261053798261195,
            -1.0417396559909513,
            0.5876314182468452
          ],
          [
            -0.9356385113620108,
            -0.48178319421200005,
            0.6621704548759562,
            0.9547763017485227,
            -1.0774526389396701,
            0.6313491825785955
          ],
          [
            -0.9638981032926204,
            -0.5277783622777473,
            0.9899776352728111,
            0.8803121599958608,
            -1.1169794694791253,
            0.6973714448536983
          ],
          [
            -0.9629524315800055,
            -0.5685294744840046,
            1.3808990488444117,
            0.8047770503587977,
            -1.1598994494159642,
            0.7917997029968209
          ],
          [
            -0.9292689217311509,
            -0.5826829438641631,
            1.6068304184829216,
            0.7306185986983424,
            -1.2049704944044786,
            0.9097378489428309
          ],
          [
            -0.8624305412327218,
            -0.5655606012776243,
            1.6692631482902718,
            0.6604363645469501,
            -1.249938628669314,
            1.0383235593658249
          ],
          [
            -0.7622485282541855,
            -0.5166788991226899,
            1.5890338225959495,
            0.596844530197568,
            -1.2923404915424124,
            1.1656459594616648
          ],
          [
            -0.6285283409603215,
            -0.4354594627042576,
            1.3483109105837552,
            0.5424641234440968,
            -1.3296607578580493,
            1.279758442731518
          ],
          [
            -0.48985751429696905,
            -0.3388706631551162,
            1.0284140184958632,
            0.4987674635804237,
            -1.360006597187662,
            1.3715949644170489
          ],
          [
            -0.35647854985535143,
            -0.2410951863420576,
            0.6616281605754919,
            0.46571978004487674,
            -1.3827232469659894,
            1.4363452456197865
          ],
          [
            -0.22921892497564852,
            -0.1492860858287229,
            0.37072263763165586,
            0.442868032672996,
            -1.3979996592197617,
            1.4756321984585172
          ],
          [
            -0.10924539012602022,
            -0.06768574097380119,
            0.20771170070138195,
            0.42968837026251044,
            -1.4064755992021896,
            1.497644933051785
          ],
          [
            0,
            0,
            0,
            0.425475,
            -1.4091,
            1.5049575574922025
          ]
        ],
        "controls": [
          [
            0.23872215639768482,
            0.7612739060795888,
            -2.1548989348184956e-06
          ],
          [
            0.24972472857865985,
            0.750271655808817,
            -1.4607855641536994e-06
          ],
          [
            0.2629118649481342,
            0.7370844636560391,
            -1.025520676170357e-06
          ],
          [
            0.2786123671306991,
            0.7213836178337436,
            -7.001494206864956e-07
          ],
          [
            0.2971987269412506,
            0.7027965726392513,
            -4.247311688058693e-07
          ],
          [
            0.319092835324376,
            0.6809012037073519,
            -1.6853082664927798e-07
          ],
          [
            0.34477208621237526,
            0.655219338152336,
            9.7531088238043e-08
          ],
          [
            0.37477500064069963,
            0.6252083809747421,
            4.945766953214293e-07
          ],
          [
            0.40125759171936115,
            0.5817636732055109,
            0.0009543652819655335
          ],
          [
            0.1318036941740061,
            0.23114851487126098,
            -0.0014810346233210276
          ],
          [
            -0.1630601325298057,
            -0.15762083199156834,
            0.000534197418222742
          ],
          [
            -0.44838801492441843,
            -0.5514867893988084,
            4.2276219755582004e-07
          ],
          [
            -0.3858999422793249,
            -0.6140899757112611,
            -4.836753192873077e-07
          ],
          [
            -0.31395912467652776,
            -0.6860357728065656,
            -7.407367822658254e-07
          ],
          [
            -0.23135859210102291,
            -0.7686376835573606,
            -1.3839181565204647e-06
          ],
          [
            0.3030890990891895,
            -1.3868250807266337e-07,
            -4.263225674167696e-08
          ],
          [
            0.07598908830197754,
            -1.688965177327037e-08,
            -1.747817050238014e-08
          ],
          [
            0.07598908774308441,
            -5.55849511214411e-09,
            -6.66478982007113e-09
          ],
          [
            0.07598908774308487,
            3.9975834720839894e-09,
            4.111910077335387e-09
          ],
          [
            0.07598908774308163,
            1.2865995219308866e-08,
            1.2256852875190567e-08
          ],
          [
            0.07598908774307747,
            2.1156994461261308e-08,
            1.690851876459935e-08
          ],
          [
            0.07598908774307436,
            2.9074413440899673e-08,
            1.7365846853556486e-08
          ],
          [
            0.07598908774307236,
            3.681127514704586e-08,
            1.3608268828580643e-08
          ],
          [
            0.07598908774307006,
            4.454008016671743e-08,
            6.5671282979820694e-09
          ],
          [
            0.07598908774306565,
            5.235347606440771e-08,
            -1.4916287938064076e-09
          ],
          [
            0.07598908774305856,
            6.025592201328434e-08,
            -7.17763226762108e-09
          ],
          [
            0.07598908699713992,
            6.649396317493619e-08,
            6.489924182513891e-09
          ],
          [
            -0.22710001153313691,
            -1.1657480073416104e-07,
            -1.863971029898685e-09
          ],
          [
            -0.3629463147886485,
            -0.13473985317098894,
            0.5023122290423214
          ],
          [
            -0.5502208597406252,
            -0.0730667724781444,
            0.376710578654952
          ],
          [
            -0.7521094465231752,
            -6.089274717466117e-05,
            0.24782758261737137
          ],
          [
            -0.8750757168795721,
            -1.2949434803190642e-05,
            0.12490881429594757
          ],
          [
            -0.946479076788281,
            -8.654340852478983e-06,
            0.05350918014171848
          ],
          [
            -0.9757361876557058,
            -8.174651652007413e-06,
            0.024251844831751603
          ],
          [
            -0.9731197798669422,
            -9.776917532965186e-06,
            0.026865769663072185
          ],
          [
            -0.9450124608965468,
            -1.4439438187099698e-05,
            0.054967243494102785
          ],
          [
            -0.8946137528491654,
            -2.7316250778442467e-05,
            0.10535127366476357
          ],
          [
            -0.8236706318482137,
            -9.444274681074579e-05,
            0.17622396314019284
          ],
          [
            -0.7272047041578386,
            -0.013721979345331058,
            0.2590534222903795
          ],
          [
            -0.6049923428972912,
            -0.04907970831839885,
            0.34579246065317754
          ],
          [
            -0.38226225905257505,
            -0.030561790920066043,
            0.34867487792525936
          ],
          [
            -0.12696725978371715,
            -0.048917967209379715,
            0.321819996312689
          ],
          [
            0.13287033589969663,
            -0.13877456181672138,
            0.2735990099954646
          ],
          [
            0.38524489611625695,
            -0.3041479710829026,
            0.19166209352455493
          ],
          [
            0.48789392486473687,
            -0.39784336829494565,
            0.1142266677991954
          ],
          [
            0.504420029265416,
            -0.4598325585166541,
            0.035734217486058796
          ],
          [
            0.4882036546131241,
            -0.5117878390448314,
            -2.806229538332038e-06
          ],
          [
            0.4534265075927106,
            -0.5465642572445352,
            -6.230530873878062e-06
          ],
          [
            0.3989487515715705,
            -0.5523368106552474,
            -0.048712634344473066
          ]
        ],
        "waypoint_times": [
          0,
          1.3673072205995973,
          5.219159572878146,
          6.864470917387889
        ],
        "totalTime": 6.864470917387889
      },
      "followsTrajectoryId": null
    },
    {
      "id": "f8ce562d-5daf-464f-a0f5-84a80fd55a65",
      "name": "intake_2",
      "waypoints": [
        {
          "x": 0.425475,
          "y": -1.4091,
          "heading": 1.5049575574922025,
          "stop": true,
          "v_max": 3,
          "omega_max": 10,
          "type": "constrained",
          "intake_x": -0.9117500000000001,
          "intake_y": 0.4392,
          "intake_distance": 0.5,
          "intake_velocity_max": 1,
          "intake_velocity_slack": 0.1
        },
        {
          "x": 0.7,
          "y": -0.31537000465393067,
          "heading": 0,
          "stop": false,
          "v_max": 3,
          "omega_max": 10,
          "type": "constrained",
          "intake_x": -1.456175,
          "intake_y": -0.315675,
          "intake_distance": 0.5,
          "intake_velocity_max": 1,
          "intake_velocity_slack": 0.1
        },
        {
          "x": 1.34,
          "y": -0.31537000465393067,
          "heading": 0,
          "stop": false,
          "v_max": 3,
          "omega_max": 10,
          "type": "constrained",
          "intake_x": -1.922825,
          "intake_y": -0.30195,
          "intake_distance": 0.5,
          "intake_velocity_max": 1,
          "intake_velocity_slack": 0.1
        },
        {
          "x": 0.4392,
          "y": -1.441125,
          "heading": 1.5707963267948966,
          "stop": true,
          "v_max": 3,
          "omega_max": 10,
          "type": "constrained",
          "intake_x": -1.071875,
          "intake_y": 0.6405,
          "intake_distance": 0.5,
          "intake_velocity_max": 1,
          "intake_velocity_slack": 0.1
        }
      ],
      "constraints": [
        {
          "id": "0a65cc1e-dd7b-4d7b-8d61-0078f2c1ecd4",
          "type": "max-velocity",
          "fromWaypoint": 1,
          "toWaypoint": 2,
          "params": {
            "v_max": 0.22999999999999998
          },
          "enabled": true
        },
        {
          "id": "afdbb06b-b433-4677-934f-2f8354112af6",
          "type": "circle-obstacle",
          "fromWaypoint": 0,
          "toWaypoint": 3,
          "params": {
            "cx": 1.020225,
            "cy": 0.2013,
            "radius": 0.3
          },
          "enabled": true
        },
        {
          "id": "3ffb6a0c-80c4-4d63-a650-25fd4619db75",
          "type": "heading-tangent",
          "fromWaypoint": 1,
          "toWaypoint": 2,
          "params": {},
          "enabled": true
        }
      ],
      "eventMarkers": [
        {
          "waypointIndex": 2,
          "percentage": 0.9,
          "name": "shoot",
          "timestamp": 5.988023174840608
        }
      ],
      "solverSettings": {
        "samplesPerMeter": 20,
        "minSamplesPerSegment": 3,
        "controlEffortWeight": 0.03
      },
      "trajectory": {
        "times": [
          0,
          0.06961757043214686,
          0.13923514086429373,
          0.2088527112964406,
          0.27847028172858745,
          0.34808785216073435,
          0.41770542259288124,
          0.48732299302502813,
          0.556940563457175,
          0.6265581338893219,
          0.6961757043214688,
          0.7657932747536157,
          0.8354108451857626,
          0.9050284156179095,
          0.9746459860500564,
          1.0442635564822031,
          1.11388112691435,
          1.183498697346497,
          1.2531162677786438,
          1.3227338382107907,
          1.3923514086429376,
          1.4619689790750845,
          1.5315865495072314,
          1.6012041199393783,
          1.8179572296572042,
          2.0347103393750303,
          2.2514634490928565,
          2.4682165588106826,
          2.6849696685285087,
          2.901722778246335,
          3.118475887964161,
          3.335228997681987,
          3.5519821073998132,
          3.7687352171176394,
          3.9854883268354655,
          4.202241436553291,
          4.418994546271117,
          4.486980878105882,
          4.5549672099406475,
          4.622953541775413,
          4.690939873610178,
          4.7589262054449435,
          4.826912537279709,
          4.894898869114474,
          4.9628852009492395,
          5.030871532784005,
          5.09885786461877,
          5.166844196453535,
          5.234830528288301,
          5.302816860123066,
          5.370803191957831,
          5.438789523792597,
          5.506775855627362,
          5.574762187462127,
          5.642748519296893,
          5.710734851131658,
          5.778721182966423,
          5.846707514801189,
          5.914693846635954,
          5.982680178470719,
          6.050666510305485,
          6.11865284214025,
          6.186639173975015,
          6.254625505809781,
          6.322611837644546,
          6.390598169479311
        ],
        "states": [
          [
            0,
            6.071844797809294e-32,
            -5.406133172668851e-30,
            0.425475,
            -1.4091,
            1.5049575574922025
          ],
          [
            0.009840406860068289,
            0.14522114693443716,
            -0.1376202905898651,
            0.42581750469973134,
            -1.4039875981993175,
            1.4997409270138455
          ],
          [
            0.02044139097718155,
            0.28153807507167633,
            -0.2097166231058245,
            0.42686517163597176,
            -1.3890781510724945,
            1.4874272553941823
          ],
          [
            0.03248828026203619,
            0.40861428433027064,
            -0.2544744732546316,
            0.4286979985112232,
            -1.3650034443943388,
            1.4711307039359245
          ],
          [
            0.04628646291161304,
            0.5259908368450399,
            -0.2967465400079945,
            0.43142848218547336,
            -1.3324228924688761,
            1.4518124457210904
          ],
          [
            0.062018212905239185,
            0.6331391042897405,
            -0.3525532478708474,
            0.43518484314496647,
            -1.2920301867855393,
            1.429038265234112
          ],
          [
            0.07989015465873373,
            0.7294808782133205,
            -0.4321082037895153,
            0.44010814768589124,
            -1.2445573923869369,
            1.401478756975253
          ],
          [
            0.10019355385832202,
            0.8143979414273296,
            -0.5416642926259561,
            0.44635653753610705,
            -1.1907780102444212,
            1.3672436039527667
          ],
          [
            0.12329567930551236,
            0.8872486166780684,
            -0.6844262728745754,
            0.4541111765554985,
            -1.1315091272616462,
            1.3241227207063273
          ],
          [
            0.1495797905979774,
            0.9474051205329961,
            -0.8607241895778588,
            0.4635797560465151,
            -1.0676116973978047,
            1.2697918830742467
          ],
          [
            0.17854247079915883,
            0.9942132712933381,
            -1.0625772434546192,
            0.4749662410302491,
            -0.9999913586179275,
            1.2022189205485752
          ],
          [
            0.20236124252181287,
            1.026899571248945,
            -1.2367781497529085,
            0.4881836933474639,
            -0.9296073031254606,
            1.1216416202499562
          ],
          [
            0.2227431596861976,
            1.042367762249889,
            -1.360287865223572,
            0.5029400025889849,
            -0.8575520083875104,
            1.0308583748109155
          ],
          [
            0.23998111139331088,
            1.0397738286063545,
            -1.4429517068955675,
            0.5190111326515974,
            -0.7850548706503332,
            0.9330249855122741
          ],
          [
            0.2539608469148837,
            1.0190647210553412,
            -1.4970824092533368,
            0.5361775941978927,
            -0.713376304301551,
            0.8305183167063901
          ],
          [
            0.26452409009025857,
            0.9801688695174634,
            -1.528336549410936,
            0.5542094611172214,
            -0.6437810280710806,
            0.7251103581852805
          ],
          [
            0.27150494790254576,
            0.9229967401191331,
            -1.538729697691733,
            0.5728647936193211,
            -0.5775393387094496,
            0.6183173184786512
          ],
          [
            0.27476351261807996,
            0.8474291137431158,
            -1.5282978363796005,
            0.591890338130418,
            -0.5159287176597501,
            0.5115901252116344
          ],
          [
            0.27421227835181666,
            0.7532924890111695,
            -1.4955848900512447,
            0.6110242406200344,
            -0.46023668381218036,
            0.4064337589041007
          ],
          [
            0.2698305992338044,
            0.6403249907916879,
            -1.4369940499420528,
            0.6300001173548266,
            -0.4117657015957449,
            0.30453571508112853
          ],
          [
            0.2616643044322322,
            0.5081389930413059,
            -1.3449246544018167,
            0.648551471502478,
            -0.3718406046736857,
            0.2079856602784087
          ],
          [
            0.2501709999012116,
            0.35668741101604695,
            -1.198442613466888,
            0.6664275119069493,
            -0.3418007035510593,
            0.11990781710199316
          ],
          [
            0.2412695957725103,
            0.191884544169996,
            -0.8876769003526247,
            0.6835934527298768,
            -0.3227757573214861,
            0.04825502950172611
          ],
          [
            0.22884476803369455,
            0.023021742718089204,
            -0.5304012522790138,
            0.7,
            -0.31537000465393067,
            0
          ],
          [
            0.22923236527116306,
            0.018774632517771634,
            0.06486066982261589,
            0.7496476601539673,
            -0.31075889627194303,
            -0.01851052748481008
          ],
          [
            0.22888369434726683,
            0.022632247101006902,
            0.08257708060930678,
            0.7992975449122868,
            -0.30626895701791895,
            -0.0015810276784424815
          ],
          [
            0.22877584419383765,
            0.02369762122514229,
            0.04831830495214064,
            0.8488985390981385,
            -0.30126028972592206,
            0.010766556704737695
          ],
          [
            0.22877881134712197,
            0.023668958307758343,
            0.03643170887011915,
            0.8984876836493788,
            -0.29613726292166254,
            0.019313608491750234
          ],
          [
            0.22878181303862244,
            0.023639926619193393,
            0.031717188699994035,
            0.948077263119646,
            -0.29101808605043117,
            0.02644635896694192
          ],
          [
            0.22878271477645956,
            0.023631198177540884,
            0.02897002024668761,
            0.9976671755874047,
            -0.28590193243785544,
            0.03287601005628993
          ],
          [
            0.22878268343630956,
            0.02363150159236383,
            0.026291168804320204,
            1.0472571287982595,
            -0.2807860503930295,
            0.03872127385068058
          ],
          [
            0.2287815257148223,
            0.02364270710935999,
            0.02147003421989587,
            1.0968468928068196,
            -0.27566822259575097,
            0.04363875503599024
          ],
          [
            0.22877764123247973,
            0.023680265623914436,
            0.007517329812048366,
            1.146435977918936,
            -0.2705436713029086,
            0.04603157068102748
          ],
          [
            0.22877801178475016,
            0.023676685407399485,
            -0.039684886794424584,
            1.1960243051942872,
            -0.2654115995739408,
            0.04001237952395886
          ],
          [
            0.2290057573273188,
            0.021361815545726064,
            -0.17388705186769493,
            1.2456375833629936,
            -0.2605281076518244,
            0.009664584267667031
          ],
          [
            0.22884607535341128,
            -0.0230095602142832,
            -0.0006259609844966965,
            1.2952836128964522,
            -0.26087013876015797,
            4.90634378293997e-05
          ],
          [
            0.1852862019919551,
            -0.46192831733582,
            -9.142547241495114e-05,
            1.34,
            -0.31537000465393067,
            0
          ],
          [
            0.11673991229706565,
            -0.4767042175808896,
            0.6538923349161203,
            1.350235687446218,
            -0.34727676914137184,
            0.02415272390513934
          ],
          [
            0.04582610398516265,
            -0.4893786821095493,
            0.982720932211579,
            1.3557213138348512,
            -0.38010206449326644,
            0.08075578548351148
          ],
          [
            -0.030421926146134624,
            -0.5002647823503742,
            1.1001022245832872,
            1.3561988508750702,
            -0.4137168900576288,
            0.15190358172779783
          ],
          [
            -0.11243913355489063,
            -0.5115147050957162,
            1.0852621648465703,
            1.3512927323485109,
            -0.44807719006450225,
            0.2261472871258281
          ],
          [
            -0.19874948381416496,
            -0.5254077972626101,
            0.9958888671343806,
            1.3406622298786255,
            -0.4832901769204998,
            0.29662872465169476
          ],
          [
            -0.28680182335169657,
            -0.5434030804894038,
            0.8739249271110052,
            1.3241037571574148,
            -0.5195894587604399,
            0.359830062330623
          ],
          [
            -0.37376719091385724,
            -0.5658993156694457,
            0.749084640573776,
            1.3015967881003967,
            -0.5572701887504157,
            0.41463326344275053
          ],
          [
            -0.45707977284177603,
            -0.5924285896700776,
            0.6417114647862051,
            1.2733039222448042,
            -0.5966233623189282,
            0.4615942872980403
          ],
          [
            -0.5346829813730649,
            -0.6220033602698019,
            0.5652814610863189,
            1.2395442813376327,
            -0.637889015474479,
            0.5023984804519435
          ],
          [
            -0.6050553422761864,
            -0.6534414437719196,
            0.5284541076637724,
            1.2007578959208411,
            -0.6812324694822668,
            0.5394694471155055
          ],
          [
            -0.6671127130063281,
            -0.6856012378704364,
            0.5365365838032944,
            1.1574727282389514,
            -0.7267396070193938,
            0.575695679740361
          ],
          [
            -0.7200575816338187,
            -0.7175252903164868,
            0.5922824111498581,
            1.1102802412034654,
            -0.7744249390009282,
            0.6142321512732005
          ],
          [
            -0.7632119959344388,
            -0.7485152905858627,
            0.6959744307853915,
            1.059821799402723,
            -0.8242470315763387,
            0.6583297666122041
          ],
          [
            -0.7958453050712478,
            -0.7781592121788992,
            0.8446910876901343,
            1.0067866084117452,
            -0.8761273882611573,
            0.7111402857719158
          ],
          [
            -0.8167332273976434,
            -0.8002915540387849,
            0.9714930744691036,
            0.951933572309744,
            -0.9297635073154498,
            0.773251950882897
          ],
          [
            -0.8255062213380019,
            -0.8109879003745165,
            1.0506292600393972,
            0.8960772177174045,
            -0.9845123630024274,
            0.8422235864351824
          ],
          [
            -0.8221678850025564,
            -0.8101849536698924,
            1.1013204248107547,
            0.8400432750531118,
            -1.0395966301949802,
            0.9155246079880612
          ],
          [
            -0.8067075222817204,
            -0.7977312153523647,
            1.1330239771163666,
            0.7846571308350272,
            -1.094230883587477,
            0.9915705108544919
          ],
          [
            -0.7791030776049339,
            -0.773407615811979,
            1.1490936911951184,
            0.730744998541329,
            -1.147616624784887,
            1.0691942893303548
          ],
          [
            -0.7393200028293826,
            -0.7369464720122192,
            1.1491178690553554,
            0.6791348333414586,
            -1.1989384612244118,
            1.1473178474876053
          ],
          [
            -0.6873052813787754,
            -0.6880483011001802,
            1.1302943890588633,
            0.6306573568606317,
            -1.2473613775425272,
            1.2247467944632893
          ],
          [
            -0.6229759593924507,
            -0.6263958715855914,
            1.0879499204671157,
            0.5861475809634201,
            -1.2920289766665192,
            1.3000271087284678
          ],
          [
            -0.5462023475263016,
            -0.5516637801570855,
            1.0151000257794671,
            0.5464472110125572,
            -1.3320624571832629,
            1.3713016711014496
          ],
          [
            -0.45678768586881074,
            -0.4635215632371565,
            0.9007425989513204,
            0.5124082011119248,
            -1.3665599204275036,
            1.4360900986502956
          ],
          [
            -0.35521419845097796,
            -0.36225047301257096,
            0.7164351513122792,
            0.4848707678048772,
            -1.3946163845415414,
            1.4905197470923732
          ],
          [
            -0.2557827879314356,
            -0.26073133880504495,
            0.4332491222811375,
            0.4641612048308963,
            -1.4157735330308037,
            1.528766315591484
          ],
          [
            -0.1636517921160702,
            -0.16582840074874047,
            0.26197999284441204,
            0.4499537385960781,
            -1.4302488305620198,
            1.5518944484124328
          ],
          [
            -0.07752218916019707,
            -0.07784574214056597,
            0.15839467360640458,
            0.4417992063048753,
            -1.4385055507407885,
            1.5658789419861507
          ],
          [
            0,
            0,
            0,
            0.4392,
            -1.441125,
            1.5707963267948966
          ]
        ],
        "controls": [
          [
            0.9370720804382752,
            -4.830820858491513e-06,
            -0.06291823405204251
          ],
          [
            0.9417018771592297,
            -6.240165748240289e-06,
            -0.05828644202229912
          ],
          [
            0.9409310884624498,
            -7.857343085286217e-06,
            -0.05905482425584928
          ],
          [
            0.9338281875650007,
            -9.818851498037839e-06,
            -0.06615470735622173
          ],
          [
            0.9198575884237337,
            -1.2176457508665552e-05,
            -0.08012148881301939
          ],
          [
            0.8987259539258892,
            -1.4692481709142594e-05,
            -0.10124844877584005
          ],
          [
            0.8703646902594298,
            -1.6524479523105295e-05,
            -0.12960430649420102
          ],
          [
            0.8350162926042847,
            -1.5845798636023e-05,
            -0.1649461551634462
          ],
          [
            0.7933992848279869,
            -6.566682784397143e-06,
            -0.20654945312152065
          ],
          [
            0.7445367870284124,
            0.00472005425991855,
            -0.25067532360933154
          ],
          [
            0.669373945970969,
            0.05504897514794068,
            -0.27517816838577386
          ],
          [
            0.5723030452871901,
            0.08201590146728827,
            -0.284059302441261
          ],
          [
            0.4661352984393376,
            0.08980833149884894,
            -0.2881133826054699
          ],
          [
            0.3577220133837869,
            0.0769253803814309,
            -0.2902802187803285
          ],
          [
            0.25115123932542416,
            0.039712172497390556,
            -0.2897824937235075
          ],
          [
            0.15116888142598978,
            -0.02407952939328312,
            -0.28599651057946673
          ],
          [
            0.06281618989613368,
            -0.11538383529715135,
            -0.27838813283353964
          ],
          [
            -0.009003808896613896,
            -0.23388897153569188,
            -0.26628183228053404
          ],
          [
            -0.06003523833937563,
            -0.3781761090454108,
            -0.24843094567068547
          ],
          [
            -0.08729236286708472,
            -0.5459756711957993,
            -0.22234307704742864
          ],
          [
            -0.08718485384103447,
            -0.7317490744958746,
            -0.18052367760498902
          ],
          [
            -0.02630676713481247,
            -0.895200788477552,
            -0.07845962367270587
          ],
          [
            -1.125057662570509e-05,
            -0.9999578816464423,
            -8.68840156028064e-06
          ],
          [
            0.09751672079761527,
            0.005148929564732179,
            0.05253724091947959
          ],
          [
            0.09582449318546747,
            0.018982331530853734,
            0.01640425533293606
          ],
          [
            0.0964584601053636,
            0.01274853964086153,
            0.006554828257006231
          ],
          [
            0.0967309755725284,
            0.009734986572010463,
            0.005893412997862629
          ],
          [
            0.09679273387762759,
            0.008876940942328751,
            0.005515037956673015
          ],
          [
            0.09683956698648356,
            0.008160547528905653,
            0.005143692212319801
          ],
          [
            0.0968799190272962,
            0.007492292074997858,
            0.004655389020581888
          ],
          [
            0.09691228312286969,
            0.00690881329850079,
            0.0036220819326600474
          ],
          [
            0.09693141424820674,
            0.006533886179638452,
            0.00043165640985909056
          ],
          [
            0.09693168330780984,
            0.006546776042073363,
            -0.010522387253210159
          ],
          [
            0.09719063652104463,
            0.0030623478513182372,
            -0.04115238862621344
          ],
          [
            0.09646023852073342,
            -0.08937842500287387,
            0.011702584967127746
          ],
          [
            5.440620988620588e-07,
            -0.9999782640940179,
            1.9635403084910404e-05
          ],
          [
            -0.37575308837173904,
            -0.319802498359304,
            0.30444229606263584
          ],
          [
            -0.4318239802892315,
            -0.29475969749168607,
            0.2734140757917264
          ],
          [
            -0.5119982346062902,
            -0.2525124499704969,
            0.23548688473690932
          ],
          [
            -0.5970978760436138,
            -0.20736705445047604,
            0.19553238121687316
          ],
          [
            -0.6748226293062586,
            -0.16707142769567848,
            0.15810290467761423
          ],
          [
            -0.738452382822892,
            -0.13506012946785628,
            0.12648398372312789
          ],
          [
            -0.7853503185564646,
            -0.11194448614225522,
            0.10270107736275375
          ],
          [
            -0.8154951768379365,
            -0.09664022381108255,
            0.0878596675588128
          ],
          [
            -0.8302834075565807,
            -0.08720427839805633,
            0.08250627823453689
          ],
          [
            -0.8316885482983524,
            -0.08142540683126541,
            0.08687843971726184
          ],
          [
            -0.8217362812894781,
            -0.07724466727028283,
            0.10100902419757747
          ],
          [
            -0.8022056967013375,
            -0.07309413893998457,
            0.12468581668807224
          ],
          [
            -0.7744801931327893,
            -0.06822985775574418,
            0.1572653070415976
          ],
          [
            -0.7395051126804494,
            -0.0631000585036571,
            0.19730775193846942
          ],
          [
            -0.6697137588951029,
            -0.03210364706174575,
            0.21447235700297151
          ],
          [
            -0.5734791875815158,
            0.0111283315009173,
            0.2156158984890457
          ],
          [
            -0.46800777144736977,
            0.04406782160122498,
            0.21693611219912326
          ],
          [
            -0.3540712909627241,
            0.06255751817893,
            0.21742471843834557
          ],
          [
            -0.23312330518922794,
            0.06330190227483652,
            0.2159805533190386
          ],
          [
            -0.1071257224099488,
            0.043611901633036174,
            0.21146778105252945
          ],
          [
            0.021620308749685242,
            0.0013899139219316296,
            0.20269779017341052
          ],
          [
            0.15071463030382082,
            -0.0647464938744061,
            0.18828380075899825
          ],
          [
            0.27802929403621024,
            -0.15526756479928533,
            0.16628990016731382
          ],
          [
            0.40227098972952247,
            -0.269474256746794,
            0.13356040332006325
          ],
          [
            0.5192896040234892,
            -0.4004305380199952,
            0.07995141011559714
          ],
          [
            0.5448692588250376,
            -0.45510079672965803,
            2.637816082072325e-06
          ],
          [
            0.5295115079425359,
            -0.4704731751109018,
            -6.9343104812893296e-06
          ],
          [
            0.5151277275575687,
            -0.4848540175835984,
            -1.403949694200876e-05
          ],
          [
            0.4806448819969342,
            -0.47476050664649044,
            -0.044592079225791434
          ]
        ],
        "waypoint_times": [
          0,
          1.6012041199393783,
          4.418994546271117,
          6.390598169479311
        ],
        "totalTime": 6.390598169479311
      },
      "followsTrajectoryId": "56629481-2539-4cde-aa12-615cc108e599"
    },
    {
      "id": "532fc13d-1759-47ef-86f5-8dc6e38af625",
      "name": "zero",
      "waypoints": [
        {
          "x": 0.4392,
          "y": -1.441125,
          "heading": 1.5707963267948966,
          "stop": true,
          "v_max": 3,
          "omega_max": 10,
          "type": "constrained",
          "intake_x": -1.044425,
          "intake_y": 0.57645,
          "intake_distance": 0.5,
          "intake_velocity_max": 1,
          "intake_velocity_slack": 0.1
        },
        {
          "x": 0.7,
          "y": -1.011075,
          "heading": 6.251449933651129,
          "stop": true,
          "v_max": 3,
          "omega_max": 10,
          "type": "constrained",
          "intake_x": -1.355525,
          "intake_y": -0.965325,
          "intake_distance": 0.5,
          "intake_velocity_max": 1,
          "intake_velocity_slack": 0.1
        }
      ],
      "constraints": [
        {
          "id": "c00574e5-1b30-4818-ab76-dba03cb30209",
          "type": "heading-tangent",
          "fromWaypoint": 1,
          "toWaypoint": 2,
          "params": {},
          "enabled": true
        }
      ],
      "eventMarkers": [],
      "solverSettings": {
        "samplesPerMeter": 20,
        "minSamplesPerSegment": 3,
        "controlEffortWeight": 0.03
      },
      "trajectory": {
        "times": [
          0,
          0.11112242956777924,
          0.22224485913555847,
          0.3333672887033377,
          0.44448971827111694,
          0.5556121478388962,
          0.6667345774066755,
          0.7778570069744548,
          0.8889794365422341,
          1.0001018661100134,
          1.1112242956777927,
          1.222346725245572
        ],
        "states": [
          [
            0,
            0,
            -7.122185034121721e-27,
            0.4392,
            -1.441125,
            1.5707963267948966
          ],
          [
            0.08613108841492446,
            0.102486905849676,
            -0.6735989366291516,
            0.44405403176581004,
            -1.4353019039174255,
            1.5276354782810253
          ],
          [
            0.15116005315865075,
            0.21573450937457386,
            -0.9061185787951047,
            0.457206247580979,
            -1.4174461882632874,
            1.4378848325184772
          ],
          [
            0.20364361673470655,
            0.34102802293585793,
            -0.9484860335678081,
            0.4768237392908807,
            -1.386317734003952,
            1.3344800392803822
          ],
          [
            0.25222227333271124,
            0.4630144575438771,
            -1.0391089631828108,
            0.5020270747736387,
            -1.3414456291661498,
            1.223275302133299
          ],
          [
            0.2988796659934455,
            0.5619875512078432,
            -1.3491075534922834,
            0.532497809053493,
            -1.2842994337861622,
            1.0879438308929665
          ],
          [
            0.34291073182241794,
            0.6169411306476913,
            -1.9272684501697122,
            0.567992069713874,
            -1.2186033486299364,
            0.9009820633306678
          ],
          [
            0.38092447202240215,
            0.5996580908342581,
            -2.631608649524507,
            0.6081225623831529,
            -1.150834274029298,
            0.6416887151314321
          ],
          [
            0.3340018303007225,
            0.4903403929825957,
            -2.516560423003818,
            0.6479250131455357,
            -1.0903919956634354,
            0.3566296846275927
          ],
          [
            0.21274138120101843,
            0.32216332034948625,
            -1.626093800435995,
            0.6784585594738268,
            -1.045627029771851,
            0.13404002253896374
          ],
          [
            0.08706356010217382,
            0.15483286590415798,
            -0.803364866852876,
            0.6951792871190106,
            -1.0194583694064863,
            0.006060882246469834
          ],
          [
            0,
            0,
            0,
            0.7,
            -1.011075,
            -0.03173537352845779
          ]
        ],
        "controls": [
          [
            0.4269446759974145,
            -0.35092728809704116,
            -0.2221269554611151
          ],
          [
            0.5337003195490849,
            -0.2656665513190037,
            -0.20063186601157018
          ],
          [
            0.6480076161299198,
            -0.1712754782935157,
            -0.1807153330628019
          ],
          [
            0.7012005671789573,
            -0.09437272379159507,
            -0.20442459873912253
          ],
          [
            0.6723449270203347,
            -0.03420921295815413,
            -0.29344268913061133
          ],
          [
            0.5568360033694119,
            -0.004239499018798535,
            -0.4389182950014302
          ],
          [
            0.34863668878643383,
            -0.06435670962468151,
            -0.5869206941638095
          ],
          [
            -0.1221252045900665,
            -0.13842571105255408,
            -0.4463308563696791
          ],
          [
            -0.4617926806029178,
            -0.36872109553750115,
            -0.16945655684747743
          ],
          [
            -0.46030949947145444,
            -0.5117507185676453,
            -0.027929931952035747
          ],
          [
            -0.30913738799992724,
            -0.5737778003037691,
            0.11708334277359402
          ]
        ],
        "waypoint_times": [
          0,
          1.222346725245572
        ],
        "totalTime": 1.222346725245572
      },
      "followsTrajectoryId": "f8ce562d-5daf-464f-a0f5-84a80fd55a65"
    }
  ]
}